Workbook

Sheet Dashboard
A1: 📋 ZiniosEdge Invoice Status Dashboard
A2: ="Last Updated: "&TEXT(TODAY(),"DD-MMM-YYYY") -> Last Updated: 02-Sep-2026
A4: 📊 INVOICE STATUS SUMMARY
A6: Invoice Status | B6: Count
A7: Invoice Sent | B7: =COUNTIF('Main Tracker'!Q3:Q100,A7) -> 38
A8: Pending | B8: =COUNTIF('Main Tracker'!Q4:Q101,A8) -> 0
A9: Credit Note, Invoice on Aug 15 | B9: =COUNTIF('Main Tracker'!Q5:Q102,A9) -> 0
A10: Need to send Invoice | B10: =COUNTIF('Main Tracker'!Q6:Q103,A10) -> 12
A11: Hold | B11: =COUNTIF('Main Tracker'!Q7:Q104,A11) -> 0
A12: TOTAL | B12: =SUM(B7:B11) -> 50
A14: ⚠️ ACTION REQUIRED — All Invoices Not Yet Sent
A16: SL No. | B16: Date | C16: Customer | D16: License | E16: Qty | F16: Distributor | G16: Invoice Status | H16: Payment Status | I16: Amount
A17: {=IFERROR(_xlfn._xlws.FILTER('Main Tracker'!A3:A100,('Main Tracker'!Q3:Q100<>"Invoice Sent")*('Main Tracker'!Q3:Q100<>""),""),"")} -> 21 | B17: {=IFERROR(_xlfn._xlws.FILTER('Main Tracker'!B3:B100,('Main Tracker'!Q3:Q100<>"Invoice Sent")*('Main Tracker'!Q3:Q100<>""),""),"")} -> 46226 | C17: {=IFERROR(_xlfn._xlws.FILTER('Main Tracker'!C3:C100,('Main Tracker'!Q3:Q100<>"Invoice Sent")*('Main Tracker'!Q3:Q100<>""),""),"")} -> NuGRP Solutions LLP | D17: {=IFERROR(_xlfn._xlws.FILTER('Main Tracker'!F3:F100,('Main Tracker'!Q3:Q100<>"Invoice Sent")*('Main Tracker'!Q3:Q100<>""),""),"")} -> Business Basic (Annual - Annual ) | E17: {=IFERROR(_xlfn._xlws.FILTER('Main Tracker'!L3:L100,('Main Tracker'!Q3:Q100<>"Invoice Sent")*('Main Tracker'!Q3:Q100<>""),""),"")} -> 5 | F17: {=IFERROR(_xlfn._xlws.FILTER('Main Tracker'!P3:P100,('Main Tracker'!Q3:Q100<>"Invoice Sent")*('Main Tracker'!Q3:Q100<>""),""),"")} -> Redington | G17: {=IFERROR(_xlfn._xlws.FILTER('Main Tracker'!Q3:Q100,('Main Tracker'!Q3:Q100<>"Invoice Sent")*('Main Tracker'!Q3:Q100<>""),""),"")} -> Need to send invoice | H17: {=IFERROR(_xlfn._xlws.FILTER('Main Tracker'!R3:R100,('Main Tracker'!Q3:Q100<>"Invoice Sent")*('Main Tracker'!Q3:Q100<>""),""),"")} -> No | I17: {=IFERROR(_xlfn._xlws.FILTER('Main Tracker'!M3:M100,('Main Tracker'!Q3:Q100<>"Invoice Sent")*('Main Tracker'!Q3:Q100<>""),""),"")} -> 8201
A18: 0 | B18: 0 | C18: 0 | D18: Business Standard (Annual - Annual) | E18: 7 | F18: Redington | G18: Need to send invoice | H18: No | I18: 58081.1
A19: 0 | B19: 0 | C19: 0 | D19: Exchange Migration Activity (One-Time) | E19: 12 | F19: 0 | G19: Need to send invoice | H19: No | I19: 3600
A20: 28 | B20: 46241 | C20: GRP Solutions | D20: Business Basic (Annual - Annual ) | E20: 2 | F20: SoftwareOne | G20: Need to send invoice | H20: No | I20: 3280.4
A21: 29 | B21: 46241 | C21: NuGRP Solutions LLP | D21: Business Basic (Monthly - Monthly ) | E21: 2 | F21: SoftwareOne | G21: Need to send invoice | H21: No | I21: 340
A22: 44 | B22: 46252 | C22: Caritor Solutions | D22: Business Basic (Annual - Annual ) | E22: 1 | F22: SoftwareOne | G22: Need to send invoice | H22: No | I22: 1632
A23: 46 | B23: 46253 | C23: INS LABS Pvt Ltd | D23: Business Basic (Annual - Annual ) | E23: 8 | F23: SoftwareOne | G23: Need to send invoice | H23: No | I23: 8786.8
A24: 47 | B24: 46254 | C24: Academics and Beyond | D24: Business Standard (Annual - Annual) | E24: 1 | F24: SoftwareOne | G24: Need to send invoice | H24: No | I24: 8379.84
A25: 49 | B25: 46255 | C25: ER Brains IT Solutions | D25: Teams Premium (Annual - Monthly) | E25: 3 | F25: SoftwareOne | G25: Need to send invoice | H25: No | I25: 2151.5975
A26: 51 | B26: 46258 | C26: SRS Travels | D26: Business Basic (Annual - Annual ) | E26: 8 | F26: SoftwareOne | G26: Need to send invoice | H26: No | I26: 12925.44
A27: 52 | B27: 46258 | C27: Caritor Solutions | D27: Business Basic (Annual - Annual ) | E27: 40 | F27: SoftwareOne | G27: Need to send invoice | H27: No | I27: 64300.8
A32: ✅ COMPLETED — Invoice Sent
A34: SL No. | B34: Date | C34: Customer | D34: License | E34: Qty | F34: Distributor | G34: Invoice Status | H34: Payment Status | I34: Amount
A35: {=IFERROR(_xlfn._xlws.FILTER('Main Tracker'!A3:A100,'Main Tracker'!Q3:Q100="Invoice Sent",""),"")} -> 1 | B35: {=IFERROR(_xlfn._xlws.FILTER('Main Tracker'!B3:B100,'Main Tracker'!Q3:Q100="Invoice Sent",""),"")} -> 46087 | C35: {=IFERROR(_xlfn._xlws.FILTER('Main Tracker'!C3:C100,'Main Tracker'!Q3:Q100="Invoice Sent",""),"")} -> FinAks Advisory Pvt Ltd | D35: {=IFERROR(_xlfn._xlws.FILTER('Main Tracker'!F3:F100,'Main Tracker'!Q3:Q100="Invoice Sent",""),"")} -> Apps for Business (Annual - Monthly) | E35: {=IFERROR(_xlfn._xlws.FILTER('Main Tracker'!L3:L100,'Main Tracker'!Q3:Q100="Invoice Sent",""),"")} -> 1 | F35: {=IFERROR(_xlfn._xlws.FILTER('Main Tracker'!P3:P100,'Main Tracker'!Q3:Q100="Invoice Sent",""),"")} -> Redington | G35: {=IFERROR(_xlfn._xlws.FILTER('Main Tracker'!Q3:Q100,'Main Tracker'!Q3:Q100="Invoice Sent",""),"")} -> Invoice Sent | H35: {=IFERROR(_xlfn._xlws.FILTER('Main Tracker'!R3:R100,'Main Tracker'!Q3:Q100="Invoice Sent",""),"")} -> Yes | I35: {=IFERROR(_xlfn._xlws.FILTER('Main Tracker'!M3:M100,'Main Tracker'!Q3:Q100="Invoice Sent",""),"")} -> 418
A36: 2 | B36: 46190 | C36: FinAks Advisory Pvt Ltd | D36: Apps for Business (Annual - Monthly) | E36: 2 | F36: Redington | G36: Invoice Sent | H36: Yes | I36: 696.78
A37: 3 | B37: 46192 | C37: Cloudwave Technologies Pvt Ltd | D37: Business Basic (Annual - Annual ) | E37: 120 | F37: Redington | G37: Invoice Sent | H37: Not Applicable | I37: 162000
A38: 4 | B38: 46195 | C38: Cloudwave Technologies Pvt Ltd | D38: MS Exchange Online Plan 2 (Annual - Annual) | E38: 8 | F38: Redington | G38: Invoice Sent | H38: Not Applicable | I38: 51584
A39: 5 | B39: 46192 | C39: FinAks Advisory Pvt Ltd | D39: Business Basic (Annual - Annual ) | E39: 2 | F39: SoftwareOne | G39: Invoice sent | H39: No | I39: 2128.04
A40: 6 | B40: 46195 | C40: Krisam Automation Pvt Ltd | D40: MS Exchange Online Plan 2 (Annual - Annual, add-on) | E40: 1 | F40: Redington | G40: Invoice Sent | H40: Yes | I40: 3371.8
A41: 7 | B41: 46196 | C41: SRS Travels | D41: MS Exchange Online Plan 2 (Annual - Annual) | E41: 1 | F41: SoftwareOne | G41: Invoice Sent | H41: Yes | I41: 6543.6
A42: 8 | B42: 46197 | C42: Sudarrshan Tech Services | D42: MS Copilot for Business (Annual - Annual) | E42: 1 | F42: Redington | G42: Invoice Sent | H42: Yes | I42: 19034.46
A43: 9 | B43: 46199 | C43: FinAks Advisory Pvt Ltd | D43: Apps for Business (Annual - Monthly) | E43: 1 | F43: Redington | G43: Invoice Sent | H43: Yes | I43: 17.42
A44: 10 | B44: 46199 | C44: FinAks Advisory Pvt Ltd | D44: Business Basic (Annual - Annual ) | E44: 1 | F44: SoftwareOne | G44: Invoice Sent | H44: Yes | I44: 930
A45: 11 | B45: 46203 | C45: Atomstrings | D45: Business Basic (Annual - Annual ) | E45: 3 | F45: SoftwareOne | G45: Invoice Sent | H45: Yes | I45: 4176
A46: 12 | B46: 46203 | C46: Dassworld | D46: Business Basic (Annual - Annual ) | E46: 2 | F46: SoftwareOne | G46: Invoice Sent | H46: Yes | I46: 2784
A47: 13 | B47: 46203 | C47: Infiniminds Pvt Ltd | D47: Business Basic (Annual - Annual ) | E47: 60 | F47: Redington | G47: Invoice Sent | H47: Yes | I47: 81420
... A68: 48 | B68: 46254 | C68: Utthunga Technologies Pvt Ltd | D68: Planner and Project Plan 3 (Annual - Annual) | E68: 2 | F68: Tata Tele | G68: Invoice Sent | H68: No | I68: 48384
A69: 50 | B69: 46257 | C69: Shreenaths Renewables Pvt Ltd | D69: Exchange Migration Activity (One-Time) | E69: 2 | F69: 0 | G69: Invoice Sent | H69: No | I69: 600
A70: 53 | B70: 46258 | C70: Malathi Venkat Enterprises | D70: Business Basic (Annual - Annual ) | E70: 2 | F70: Redington | G70: Invoice Sent | H70: Yes | I70: 3296.64
A71: 54 | B71: 46259 | C71: Neo TVS | D71: Website Hosting Charges | E71: 1 | F71: 0 | G71: Invoice Sent | H71: No | I71: 1695
A72: 55 | B72: 46261 | C72: Sudarrshan Tech Services | D72: Business Basic (Annual - Annual ) | E72: 11 | F72: Redington | G72: Invoice Sent | H72: No | I72: 18131.52

Sheet Main Tracker
A1: SL No. | B1: Date Loaded | C1: Customer Company Name | D1: PO Number | E1: Renewal /Prorate/Net New | F1: License Description | G1: Buy Price | H1: Sell Price | I1: Prorate Price | J1: prorate Period in Days | K1: Prorate Period | L1: Qty | M1: Total Revenue | N1: P/L | O1: Margin % | P1: Backend Distributor | Q1: Invoice Status | R1: Payment Received | S1: Remarks
A2: =ROW() - ROW($A$2) -> 0
A3: =ROW() - ROW($A$2) -> 1 | B3: 46087 | C3: FinAks Advisory Pvt Ltd | E3: Prorate | F3: Apps for Business (Annual - Monthly) | G3: 525 | H3: 540 | I3: 418 | J3: {=_xlfn.LET(_xlpm.p,K3,IF(OR(_xlpm.p="",_xlpm.p="-",ISERROR(SEARCH("to",_xlpm.p))),"-",IFERROR(_xlfn.LET(_xlpm.s,TRIM(_xlfn.TEXTBEFORE(_xlpm.p,"to")),_xlpm.e,TRIM(_xlfn.TEXTAFTER(_xlpm.p,"to")),_xlpm.sd,DATE(VALUE(_xlfn.TEXTAFTER(_xlpm.s,"/",-1)),VALUE(_xlfn.TEXTBEFORE(_xlfn.TEXTAFTER(_xlpm.s,"/"),"/")),VALUE(_xlfn.TEXTBEFORE(_xlpm.s,"/"))),_xlpm.ed,DATE(VALUE(_xlfn.TEXTAFTER(_xlpm.e,"/",-1)),VALUE(_xlfn.TEXTBEFORE(_xlfn.TEXTAFTER(_xlpm.e,"/"),"/")),VALUE(_xlfn.TEXTBEFORE(_xlpm.e,"/"))),_xlpm.ed-_xlpm.sd+1),"-")))} -> 25 | K3: 03/06/2026 to 27/06/2026 | L3: 1 | M3: =IF(OR(L3="",L3="-"),"-",IF(AND(ISNUMBER(I3),I3<>0),I3*L3,IF(ISNUMBER(H3),H3*L3,"-"))) -> 418 | N3: =IF(OR(G3="",H3="",L3=""),"",(H3-G3)*L3) -> 15 | O3: =IF(OR(G3="",G3=0,H3=""),"",((H3-G3)/G3)*100) -> 2.8571429 | P3: Redington | Q3: Invoice Sent | R3: Yes
A4: =ROW() - ROW($A$2) -> 2 | B4: 46190 | C4: FinAks Advisory Pvt Ltd | E4: Prorate | F4: Apps for Business (Annual - Monthly) | G4: 525 | H4: 540 | I4: 348.39 | J4: {=_xlfn.LET(_xlpm.p,K4,IF(OR(_xlpm.p="",_xlpm.p="-",ISERROR(SEARCH("to",_xlpm.p))),"-",IFERROR(_xlfn.LET(_xlpm.s,TRIM(_xlfn.TEXTBEFORE(_xlpm.p,"to")),_xlpm.e,TRIM(_xlfn.TEXTAFTER(_xlpm.p,"to")),_xlpm.sd,DATE(VALUE(_xlfn.TEXTAFTER(_xlpm.s,"/",-1)),VALUE(_xlfn.TEXTBEFORE(_xlfn.TEXTAFTER(_xlpm.s,"/"),"/")),VALUE(_xlfn.TEXTBEFORE(_xlpm.s,"/"))),_xlpm.ed,DATE(VALUE(_xlfn.TEXTAFTER(_xlpm.e,"/",-1)),VALUE(_xlfn.TEXTBEFORE(_xlfn.TEXTAFTER(_xlpm.e,"/"),"/")),VALUE(_xlfn.TEXTBEFORE(_xlpm.e,"/"))),_xlpm.ed-_xlpm.sd+1),"-")))} -> 11 | K4: 17/06/2026 to 27/06/2026 | L4: 2 | M4: =IF(OR(L4="",L4="-"),"-",IF(AND(ISNUMBER(I4),I4<>0),I4*L4,IF(ISNUMBER(H4),H4*L4,"-"))) -> 696.78 | N4: =IF(OR(G4="",H4="",L4=""),"",(H4-G4)*L4) -> 30 | O4: =IF(OR(G4="",G4=0,H4=""),"",((H4-G4)/G4)*100) -> 2.8571429 | P4: Redington | Q4: Invoice Sent | R4: Yes
A5: =ROW() - ROW($A$2) -> 3 | B5: 46192 | C5: Cloudwave Technologies Pvt Ltd | E5: NA | F5: Business Basic (Annual - Annual ) | G5: 1331.45 | H5: 1350 | I5: - | J5: {=_xlfn.LET(_xlpm.p,K5,IF(OR(_xlpm.p="",_xlpm.p="-",ISERROR(SEARCH("to",_xlpm.p))),"-",IFERROR(_xlfn.LET(_xlpm.s,TRIM(_xlfn.TEXTBEFORE(_xlpm.p,"to")),_xlpm.e,TRIM(_xlfn.TEXTAFTER(_xlpm.p,"to")),_xlpm.sd,DATE(VALUE(_xlfn.TEXTAFTER(_xlpm.s,"/",-1)),VALUE(_xlfn.TEXTBEFORE(_xlfn.TEXTAFTER(_xlpm.s,"/"),"/")),VALUE(_xlfn.TEXTBEFORE(_xlpm.s,"/"))),_xlpm.ed,DATE(VALUE(_xlfn.TEXTAFTER(_xlpm.e,"/",-1)),VALUE(_xlfn.TEXTBEFORE(_xlfn.TEXTAFTER(_xlpm.e,"/"),"/")),VALUE(_xlfn.TEXTBEFORE(_xlpm.e,"/"))),_xlpm.ed-_xlpm.sd+1),"-")))} -> - | K5: - | L5: 120 | M5: =IF(OR(L5="",L5="-"),"-",IF(AND(ISNUMBER(I5),I5<>0),I5*L5,IF(ISNUMBER(H5),H5*L5,"-"))) -> 162000 | N5: =IF(OR(G5="",H5="",L5=""),"",(H5-G5)*L5) -> 2226 | O5: =IF(OR(G5="",G5=0,H5=""),"",((H5-G5)/G5)*100) -> 1.3932179 | P5: Redington | Q5: Invoice Sent | R5: Not Applicable | S5: PO Canceled
A6: =ROW() - ROW($A$2) -> 4 | B6: 46195 | C6: Cloudwave Technologies Pvt Ltd | E6: NA | F6: MS Exchange Online Plan 2 (Annual - Annual) | G6: 6384 | H6: 6448 | I6: - | J6: {=_xlfn.LET(_xlpm.p,K6,IF(OR(_xlpm.p="",_xlpm.p="-",ISERROR(SEARCH("to",_xlpm.p))),"-",IFERROR(_xlfn.LET(_xlpm.s,TRIM(_xlfn.TEXTBEFORE(_xlpm.p,"to")),_xlpm.e,TRIM(_xlfn.TEXTAFTER(_xlpm.p,"to")),_xlpm.sd,DATE(VALUE(_xlfn.TEXTAFTER(_xlpm.s,"/",-1)),VALUE(_xlfn.TEXTBEFORE(_xlfn.TEXTAFTER(_xlpm.s,"/"),"/")),VALUE(_xlfn.TEXTBEFORE(_xlpm.s,"/"))),_xlpm.ed,DATE(VALUE(_xlfn.TEXTAFTER(_xlpm.e,"/",-1)),VALUE(_xlfn.TEXTBEFORE(_xlfn.TEXTAFTER(_xlpm.e,"/"),"/")),VALUE(_xlfn.TEXTBEFORE(_xlpm.e,"/"))),_xlpm.ed-_xlpm.sd+1),"-")))} -> - | K6: - | L6: 8 | M6: =IF(OR(L6="",L6="-"),"-",IF(AND(ISNUMBER(I6),I6<>0),I6*L6,IF(ISNUMBER(H6),H6*L6,"-"))) -> 51584 | N6: =IF(OR(G6="",H6="",L6=""),"",(H6-G6)*L6) -> 512 | O6: =IF(OR(G6="",G6=0,H6=""),"",((H6-G6)/G6)*100) -> 1.0025063 | P6: Redington | Q6: Invoice Sent | R6: Not Applicable | S6: PO Canceled
A7: 5 | B7: 46192 | C7: FinAks Advisory Pvt Ltd | E7: Prorate | F7: Business Basic (Annual - Annual ) | G7: 1050.68 | H7: 1064.02 | I7: 1064.02 | J7: {=_xlfn.LET(_xlpm.p,K7,IF(OR(_xlpm.p="",_xlpm.p="-",ISERROR(SEARCH("to",_xlpm.p))),"-",IFERROR(_xlfn.LET(_xlpm.s,TRIM(_xlfn.TEXTBEFORE(_xlpm.p,"to")),_xlpm.e,TRIM(_xlfn.TEXTAFTER(_xlpm.p,"to")),_xlpm.sd,DATE(VALUE(_xlfn.TEXTAFTER(_xlpm.s,"/",-1)),VALUE(_xlfn.TEXTBEFORE(_xlfn.TEXTAFTER(_xlpm.s,"/"),"/")),VALUE(_xlfn.TEXTBEFORE(_xlpm.s,"/"))),_xlpm.ed,DATE(VALUE(_xlfn.TEXTAFTER(_xlpm.e,"/",-1)),VALUE(_xlfn.TEXTBEFORE(_xlfn.TEXTAFTER(_xlpm.e,"/"),"/")),VALUE(_xlfn.TEXTBEFORE(_xlpm.e,"/"))),_xlpm.ed-_xlpm.sd+1),"-")))} -> 279 | K7: 19/06/2026 to 24/03/2027 | L7: 2 | M7: =IF(OR(L7="",L7="-"),"-",IF(AND(ISNUMBER(I7),I7<>0),I7*L7,IF(ISNUMBER(H7),H7*L7,"-"))) -> 2128.04 | N7: =IF(OR(G7="",H7="",L7=""),"",(H7-G7)*L7) -> 26.68 | O7: =IF(OR(G7="",G7=0,H7=""),"",((H7-G7)/G7)*100) -> 1.2696539 | P7: SoftwareOne | Q7: Invoice sent | R7: No | S7: Need to bill along with Aug month invoice
A8: =ROW() - ROW($A$2) -> 6 | B8: 46195 | C8: Krisam Automation Pvt Ltd | E8: Prorate | F8: MS Exchange Online Plan 2 (Annual - Annual, add-on) | G8: 6384 | H8: 6511 | I8: 3371.8 | J8: {=_xlfn.LET(_xlpm.p,K8,IF(OR(_xlpm.p="",_xlpm.p="-",ISERROR(SEARCH("to",_xlpm.p))),"-",IFERROR(_xlfn.LET(_xlpm.s,TRIM(_xlfn.TEXTBEFORE(_xlpm.p,"to")),_xlpm.e,TRIM(_xlfn.TEXTAFTER(_xlpm.p,"to")),_xlpm.sd,DATE(VALUE(_xlfn.TEXTAFTER(_xlpm.s,"/",-1)),VALUE(_xlfn.TEXTBEFORE(_xlfn.TEXTAFTER(_xlpm.s,"/"),"/")),VALUE(_xlfn.TEXTBEFORE(_xlpm.s,"/"))),_xlpm.ed,DATE(VALUE(_xlfn.TEXTAFTER(_xlpm.e,"/",-1)),VALUE(_xlfn.TEXTBEFORE(_xlfn.TEXTAFTER(_xlpm.e,"/"),"/")),VALUE(_xlfn.TEXTBEFORE(_xlpm.e,"/"))),_xlpm.ed-_xlpm.sd+1),"-")))} -> 190 | K8: 22/06/2026 to 28/12/2026 | L8: 1 | M8: =IF(OR(L8="",L8="-"),"-",IF(AND(ISNUMBER(I8),I8<>0),I8*L8,IF(ISNUMBER(H8),H8*L8,"-"))) -> 3371.8 | N8: =IF(OR(G8="",H8="",L8=""),"",(H8-G8)*L8) -> 127 | O8: =IF(OR(G8="",G8=0,H8=""),"",((H8-G8)/G8)*100) -> 1.9893484 | P8: Redington | Q8: Invoice Sent | R8: Yes
A9: =ROW() - ROW($A$2) -> 7 | B9: 46196 | C9: SRS Travels | E9: Renewal | F9: MS Exchange Online Plan 2 (Annual - Annual) | G9: 6384 | H9: 6543.6 | I9: - | J9: {=_xlfn.LET(_xlpm.p,K9,IF(OR(_xlpm.p="",_xlpm.p="-",ISERROR(SEARCH("to",_xlpm.p))),"-",IFERROR(_xlfn.LET(_xlpm.s,TRIM(_xlfn.TEXTBEFORE(_xlpm.p,"to")),_xlpm.e,TRIM(_xlfn.TEXTAFTER(_xlpm.p,"to")),_xlpm.sd,DATE(VALUE(_xlfn.TEXTAFTER(_xlpm.s,"/",-1)),VALUE(_xlfn.TEXTBEFORE(_xlfn.TEXTAFTER(_xlpm.s,"/"),"/")),VALUE(_xlfn.TEXTBEFORE(_xlpm.s,"/"))),_xlpm.ed,DATE(VALUE(_xlfn.TEXTAFTER(_xlpm.e,"/",-1)),VALUE(_xlfn.TEXTBEFORE(_xlfn.TEXTAFTER(_xlpm.e,"/"),"/")),VALUE(_xlfn.TEXTBEFORE(_xlpm.e,"/"))),_xlpm.ed-_xlpm.sd+1),"-")))} -> 365 | K9: 23/06/2026 to 22/06/2027 | L9: 1 | M9: =IF(OR(L9="",L9="-"),"-",IF(AND(ISNUMBER(I9),I9<>0),I9*L9,IF(ISNUMBER(H9),H9*L9,"-"))) -> 6543.6 | N9: =IF(OR(G9="",H9="",L9=""),"",(H9-G9)*L9) -> 159.6 | O9: =IF(OR(G9="",G9=0,H9=""),"",((H9-G9)/G9)*100) -> 2.5 | P9: SoftwareOne | Q9: Invoice Sent | R9: Yes
A10: =ROW() - ROW($A$2) -> 8 | B10: 46197 | C10: Sudarrshan Tech Services | D10: 01062326.TE | E10: Net New | F10: MS Copilot for Business (Annual - Annual) | G10: 18846 | H10: 19034.46 | I10: - | J10: {=_xlfn.LET(_xlpm.p,K10,IF(OR(_xlpm.p="",_xlpm.p="-",ISERROR(SEARCH("to",_xlpm.p))),"-",IFERROR(_xlfn.LET(_xlpm.s,TRIM(_xlfn.TEXTBEFORE(_xlpm.p,"to")),_xlpm.e,TRIM(_xlfn.TEXTAFTER(_xlpm.p,"to")),_xlpm.sd,DATE(VALUE(_xlfn.TEXTAFTER(_xlpm.s,"/",-1)),VALUE(_xlfn.TEXTBEFORE(_xlfn.TEXTAFTER(_xlpm.s,"/"),"/")),VALUE(_xlfn.TEXTBEFORE(_xlpm.s,"/"))),_xlpm.ed,DATE(VALUE(_xlfn.TEXTAFTER(_xlpm.e,"/",-1)),VALUE(_xlfn.TEXTBEFORE(_xlfn.TEXTAFTER(_xlpm.e,"/"),"/")),VALUE(_xlfn.TEXTBEFORE(_xlpm.e,"/"))),_xlpm.ed-_xlpm.sd+1),"-")))} -> 365 | K10: 24/06/2026 to 23/06/2027 | L10: 1 | M10: =IF(OR(L10="",L10="-"),"-",IF(AND(ISNUMBER(I10),I10<>0),I10*L10,IF(ISNUMBER(H10),H10*L10,"-"))) -> 19034.46 | N10: =IF(OR(G10="",H10="",L10=""),"",(H10-G10)*L10) -> 188.46 | O10: =IF(OR(G10="",G10=0,H10=""),"",((H10-G10)/G10)*100) -> 1 | P10: Redington | Q10: Invoice Sent | R10: Yes
A11: =ROW() - ROW($A$2) -> 9 | B11: 46199 | C11: FinAks Advisory Pvt Ltd | E11: Prorate | F11: Apps for Business (Annual - Monthly) | G11: 525 | H11: 540 | I11: 17.42 | J11: {=_xlfn.LET(_xlpm.p,K11,IF(OR(_xlpm.p="",_xlpm.p="-",ISERROR(SEARCH("to",_xlpm.p))),"-",IFERROR(_xlfn.LET(_xlpm.s,TRIM(_xlfn.TEXTBEFORE(_xlpm.p,"to")),_xlpm.e,TRIM(_xlfn.TEXTAFTER(_xlpm.p,"to")),_xlpm.sd,DATE(VALUE(_xlfn.TEXTAFTER(_xlpm.s,"/",-1)),VALUE(_xlfn.TEXTBEFORE(_xlfn.TEXTAFTER(_xlpm.s,"/"),"/")),VALUE(_xlfn.TEXTBEFORE(_xlpm.s,"/"))),_xlpm.ed,DATE(VALUE(_xlfn.TEXTAFTER(_xlpm.e,"/",-1)),VALUE(_xlfn.TEXTBEFORE(_xlfn.TEXTAFTER(_xlpm.e,"/"),"/")),VALUE(_xlfn.TEXTBEFORE(_xlpm.e,"/"))),_xlpm.ed-_xlpm.sd+1),"-")))} -> 2 | K11: 26/06/2026 to 27/06/2026 | L11: 1 | M11: =IF(OR(L11="",L11="-"),"-",IF(AND(ISNUMBER(I11),I11<>0),I11*L11,IF(ISNUMBER(H11),H11*L11,"-"))) -> 17.42 | N11: =IF(OR(G11="",H11="",L11=""),"",(H11-G11)*L11) -> 15 | O11: =IF(OR(G11="",G11=0,H11=""),"",((H11-G11)/G11)*100) -> 2.8571429 | P11: Redington | Q11: Invoice Sent | R11: Yes
A12: =ROW() - ROW($A$2) -> 10 | B12: 46199 | C12: FinAks Advisory Pvt Ltd | E12: Prorate | F12: Business Basic (Annual - Annual ) | G12: 1336 | H12: 1392 | I12: 930 | J12: {=_xlfn.LET(_xlpm.p,K12,IF(OR(_xlpm.p="",_xlpm.p="-",ISERROR(SEARCH("to",_xlpm.p))),"-",IFERROR(_xlfn.LET(_xlpm.s,TRIM(_xlfn.TEXTBEFORE(_xlpm.p,"to")),_xlpm.e,TRIM(_xlfn.TEXTAFTER(_xlpm.p,"to")),_xlpm.sd,DATE(VALUE(_xlfn.TEXTAFTER(_xlpm.s,"/",-1)),VALUE(_xlfn.TEXTBEFORE(_xlfn.TEXTAFTER(_xlpm.s,"/"),"/")),VALUE(_xlfn.TEXTBEFORE(_xlpm.s,"/"))),_xlpm.ed,DATE(VALUE(_xlfn.TEXTAFTER(_xlpm.e,"/",-1)),VALUE(_xlfn.TEXTBEFORE(_xlfn.TEXTAFTER(_xlpm.e,"/"),"/")),VALUE(_xlfn.TEXTBEFORE(_xlpm.e,"/"))),_xlpm.ed-_xlpm.sd+1),"-")))} -> 245 | K12: 26/06/2026 to 25/02/2027 | L12: 1 | M12: =IF(OR(L12="",L12="-"),"-",IF(AND(ISNUMBER(I12),I12<>0),I12*L12,IF(ISNUMBER(H12),H12*L12,"-"))) -> 930 | N12: =IF(OR(G12="",H12="",L12=""),"",(H12-G12)*L12) -> 56 | O12: =IF(OR(G12="",G12=0,H12=""),"",((H12-G12)/G12)*100) -> 4.1916168 | P12: SoftwareOne | Q12: Invoice Sent | R12: Yes
A13: =ROW() - ROW($A$2) -> 11 | B13: 46203 | C13: Atomstrings | E13: Renewal | F13: Business Basic (Annual - Annual ) | G13: 1339.8 | H13: 1392 | I13: - | J13: {=_xlfn.LET(_xlpm.p,K13,IF(OR(_xlpm.p="",_xlpm.p="-",ISERROR(SEARCH("to",_xlpm.p))),"-",IFERROR(_xlfn.LET(_xlpm.s,TRIM(_xlfn.TEXTBEFORE(_xlpm.p,"to")),_xlpm.e,TRIM(_xlfn.TEXTAFTER(_xlpm.p,"to")),_xlpm.sd,DATE(VALUE(_xlfn.TEXTAFTER(_xlpm.s,"/",-1)),VALUE(_xlfn.TEXTBEFORE(_xlfn.TEXTAFTER(_xlpm.s,"/"),"/")),VALUE(_xlfn.TEXTBEFORE(_xlpm.s,"/"))),_xlpm.ed,DATE(VALUE(_xlfn.TEXTAFTER(_xlpm.e,"/",-1)),VALUE(_xlfn.TEXTBEFORE(_xlfn.TEXTAFTER(_xlpm.e,"/"),"/")),VALUE(_xlfn.TEXTBEFORE(_xlpm.e,"/"))),_xlpm.ed-_xlpm.sd+1),"-")))} -> 365 | K13: 30/06/2026 to 29/06/2027 | L13: 3 | M13: =IF(OR(L13="",L13="-"),"-",IF(AND(ISNUMBER(I13),I13<>0),I13*L13,IF(ISNUMBER(H13),H13*L13,"-"))) -> 4176 | N13: =IF(OR(G13="",H13="",L13=""),"",(H13-G13)*L13) -> 156.6 | O13: =IF(OR(G13="",G13=0,H13=""),"",((H13-G13)/G13)*100) -> 3.8961039 | P13: SoftwareOne | Q13: Invoice Sent | R13: Yes
A14: =ROW() - ROW($A$2) -> 12 | B14: 46203 | C14: Dassworld | E14: Renewal | F14: Business Basic (Annual - Annual ) | G14: 1339.8 | H14: 1392 | I14: - | J14: {=_xlfn.LET(_xlpm.p,K14,IF(OR(_xlpm.p="",_xlpm.p="-",ISERROR(SEARCH("to",_xlpm.p))),"-",IFERROR(_xlfn.LET(_xlpm.s,TRIM(_xlfn.TEXTBEFORE(_xlpm.p,"to")),_xlpm.e,TRIM(_xlfn.TEXTAFTER(_xlpm.p,"to")),_xlpm.sd,DATE(VALUE(_xlfn.TEXTAFTER(_xlpm.s,"/",-1)),VALUE(_xlfn.TEXTBEFORE(_xlfn.TEXTAFTER(_xlpm.s,"/"),"/")),VALUE(_xlfn.TEXTBEFORE(_xlpm.s,"/"))),_xlpm.ed,DATE(VALUE(_xlfn.TEXTAFTER(_xlpm.e,"/",-1)),VALUE(_xlfn.TEXTBEFORE(_xlfn.TEXTAFTER(_xlpm.e,"/"),"/")),VALUE(_xlfn.TEXTBEFORE(_xlpm.e,"/"))),_xlpm.ed-_xlpm.sd+1),"-")))} -> 365 | K14: 30/06/2026 to 29/06/2027 | L14: 2 | M14: =IF(OR(L14="",L14="-"),"-",IF(AND(ISNUMBER(I14),I14<>0),I14*L14,IF(ISNUMBER(H14),H14*L14,"-"))) -> 2784 | N14: =IF(OR(G14="",H14="",L14=""),"",(H14-G14)*L14) -> 104.4 | O14: =IF(OR(G14="",G14=0,H14=""),"",((H14-G14)/G14)*100) -> 3.8961039 | P14: SoftwareOne | Q14: Invoice Sent | R14: Yes
A15: =ROW() - ROW($A$2) -> 13 | B15: 46203 | C15: Infiniminds Pvt Ltd | D15: IM/PO/2026-27/017 | E15: Renewal | F15: Business Basic (Annual - Annual ) | G15: 1343.28 | H15: 1357 | I15: - | J15: {=_xlfn.LET(_xlpm.p,K15,IF(OR(_xlpm.p="",_xlpm.p="-",ISERROR(SEARCH("to",_xlpm.p))),"-",IFERROR(_xlfn.LET(_xlpm.s,TRIM(_xlfn.TEXTBEFORE(_xlpm.p,"to")),_xlpm.e,TRIM(_xlfn.TEXTAFTER(_xlpm.p,"to")),_xlpm.sd,DATE(VALUE(_xlfn.TEXTAFTER(_xlpm.s,"/",-1)),VALUE(_xlfn.TEXTBEFORE(_xlfn.TEXTAFTER(_xlpm.s,"/"),"/")),VALUE(_xlfn.TEXTBEFORE(_xlpm.s,"/"))),_xlpm.ed,DATE(VALUE(_xlfn.TEXTAFTER(_xlpm.e,"/",-1)),VALUE(_xlfn.TEXTBEFORE(_xlfn.TEXTAFTER(_xlpm.e,"/"),"/")),VALUE(_xlfn.TEXTBEFORE(_xlpm.e,"/"))),_xlpm.ed-_xlpm.sd+1),"-")))} -> 365 | K15: 30/06/2026 to 29/06/2027 | L15: 60 | M15: =IF(OR(L15="",L15="-"),"-",IF(AND(ISNUMBER(I15),I15<>0),I15*L15,IF(ISNUMBER(H15),H15*L15,"-"))) -> 81420 | N15: =IF(OR(G15="",H15="",L15=""),"",(H15-G15)*L15) -> 823.2 | O15: =IF(OR(G15="",G15=0,H15=""),"",((H15-G15)/G15)*100) -> 1.0213805 | P15: Redington | Q15: Invoice Sent | R15: Yes
A16: =ROW() - ROW($A$2) -> 14 | B16: 46203 | C16: INS LABS Pvt Ltd | E16: Renewal | F16: Exchange Online Plan 2 | G16: 6384 | H16: 7980 | J16: {=_xlfn.LET(_xlpm.p,K16,IF(OR(_xlpm.p="",_xlpm.p="-",ISERROR(SEARCH("to",_xlpm.p))),"-",IFERROR(_xlfn.LET(_xlpm.s,TRIM(_xlfn.TEXTBEFORE(_xlpm.p,"to")),_xlpm.e,TRIM(_xlfn.TEXTAFTER(_xlpm.p,"to")),_xlpm.sd,DATE(VALUE(_xlfn.TEXTAFTER(_xlpm.s,"/",-1)),VALUE(_xlfn.TEXTBEFORE(_xlfn.TEXTAFTER(_xlpm.s,"/"),"/")),VALUE(_xlfn.TEXTBEFORE(_xlpm.s,"/"))),_xlpm.ed,DATE(VALUE(_xlfn.TEXTAFTER(_xlpm.e,"/",-1)),VALUE(_xlfn.TEXTBEFORE(_xlfn.TEXTAFTER(_xlpm.e,"/"),"/")),VALUE(_xlfn.TEXTBEFORE(_xlpm.e,"/"))),_xlpm.ed-_xlpm.sd+1),"-")))} -> 365 | K16: 30/06/2026 to 29/06/2027 | L16: 3 | M16: =IF(OR(L16="",L16="-"),"-",IF(AND(ISNUMBER(I16),I16<>0),I16*L16,IF(ISNUMBER(H16),H16*L16,"-"))) -> 23940 | N16: =IF(OR(G16="",H16="",L16=""),"",(H16-G16)*L16) -> 4788 | O16: =IF(OR(G16="",G16=0,H16=""),"",((H16-G16)/G16)*100) -> 25 | P16: Redington | Q16: Invoice Sent | R16: Yes
A17: =ROW() - ROW($A$2) -> 15 | B17: 46202 | C17: NuGRP Solutions LLP | D17: NuGRP-2627-030 | E17: Net New | F17: Windows Server 2025 - 1 Device CAL | G17: 2873 | H17: 2892 | J17: {=_xlfn.LET(_xlpm.p,K17,IF(OR(_xlpm.p="",_xlpm.p="-",ISERROR(SEARCH("to",_xlpm.p))),"-",IFERROR(_xlfn.LET(_xlpm.s,TRIM(_xlfn.TEXTBEFORE(_xlpm.p,"to")),_xlpm.e,TRIM(_xlfn.TEXTAFTER(_xlpm.p,"to")),_xlpm.sd,DATE(VALUE(_xlfn.TEXTAFTER(_xlpm.s,"/",-1)),VALUE(_xlfn.TEXTBEFORE(_xlfn.TEXTAFTER(_xlpm.s,"/"),"/")),VALUE(_xlfn.TEXTBEFORE(_xlpm.s,"/"))),_xlpm.ed,DATE(VALUE(_xlfn.TEXTAFTER(_xlpm.e,"/",-1)),VALUE(_xlfn.TEXTBEFORE(_xlfn.TEXTAFTER(_xlpm.e,"/"),"/")),VALUE(_xlfn.TEXTBEFORE(_xlpm.e,"/"))),_xlpm.ed-_xlpm.sd+1),"-")))} -> - | K17: Perpetual | L17: 18 | M17: =IF(OR(L17="",L17="-"),"-",IF(AND(ISNUMBER(I17),I17<>0),I17*L17,IF(ISNUMBER(H17),H17*L17,"-"))) -> 52056 | N17: =IF(OR(G17="",H17="",L17=""),"",(H17-G17)*L17) -> 342 | O17: =IF(OR(G17="",G17=0,H17=""),"",((H17-G17)/G17)*100) -> 0.66132962 | P17: Tata Tele | Q17: Invoice Sent | R17: Yes
A18: =ROW() - ROW($A$2) -> 16 | B18: 46202 | C18: NuGRP Solutions LLP | D18: NuGRP-2627-030 | E18: Net New | F18: SQL Server 2025 Standard Edition | G18: 71667.65 | H18: 72310 | J18: {=_xlfn.LET(_xlpm.p,K18,IF(OR(_xlpm.p="",_xlpm.p="-",ISERROR(SEARCH("to",_xlpm.p))),"-",IFERROR(_xlfn.LET(_xlpm.s,TRIM(_xlfn.TEXTBEFORE(_xlpm.p,"to")),_xlpm.e,TRIM(_xlfn.TEXTAFTER(_xlpm.p,"to")),_xlpm.sd,DATE(VALUE(_xlfn.TEXTAFTER(_xlpm.s,"/",-1)),VALUE(_xlfn.TEXTBEFORE(_xlfn.TEXTAFTER(_xlpm.s,"/"),"/")),VALUE(_xlfn.TEXTBEFORE(_xlpm.s,"/"))),_xlpm.ed,DATE(VALUE(_xlfn.TEXTAFTER(_xlpm.e,"/",-1)),VALUE(_xlfn.TEXTBEFORE(_xlfn.TEXTAFTER(_xlpm.e,"/"),"/")),VALUE(_xlfn.TEXTBEFORE(_xlpm.e,"/"))),_xlpm.ed-_xlpm.sd+1),"-")))} -> - | K18: Perpetual | L18: 1 | M18: =IF(OR(L18="",L18="-"),"-",IF(AND(ISNUMBER(I18),I18<>0),I18*L18,IF(ISNUMBER(H18),H18*L18,"-"))) -> 72310 | N18: =IF(OR(G18="",H18="",L18=""),"",(H18-G18)*L18) -> 642.35 | O18: =IF(OR(G18="",G18=0,H18=""),"",((H18-G18)/G18)*100) -> 0.89629003 | P18: Tata Tele | Q18: Invoice Sent | R18: Yes
A19: =ROW() - ROW($A$2) -> 17 | B19: 46202 | C19: NuGRP Solutions LLP | D19: NuGRP-2627-030 | E19: Net New | F19: SQL Server 2025 - 1 User CAL | G19: 16680 | H19: 16813 | J19: {=_xlfn.LET(_xlpm.p,K19,IF(OR(_xlpm.p="",_xlpm.p="-",ISERROR(SEARCH("to",_xlpm.p))),"-",IFERROR(_xlfn.LET(_xlpm.s,TRIM(_xlfn.TEXTBEFORE(_xlpm.p,"to")),_xlpm.e,TRIM(_xlfn.TEXTAFTER(_xlpm.p,"to")),_xlpm.sd,DATE(VALUE(_xlfn.TEXTAFTER(_xlpm.s,"/",-1)),VALUE(_xlfn.TEXTBEFORE(_xlfn.TEXTAFTER(_xlpm.s,"/"),"/")),VALUE(_xlfn.TEXTBEFORE(_xlpm.s,"/"))),_xlpm.ed,DATE(VALUE(_xlfn.TEXTAFTER(_xlpm.e,"/",-1)),VALUE(_xlfn.TEXTBEFORE(_xlfn.TEXTAFTER(_xlpm.e,"/"),"/")),VALUE(_xlfn.TEXTBEFORE(_xlpm.e,"/"))),_xlpm.ed-_xlpm.sd+1),"-")))} -> - | K19: Perpetual | L19: 6 | M19: =IF(OR(L19="",L19="-"),"-",IF(AND(ISNUMBER(I19),I19<>0),I19*L19,IF(ISNUMBER(H19),H19*L19,"-"))) -> 100878 | N19: =IF(OR(G19="",H19="",L19=""),"",(H19-G19)*L19) -> 798 | O19: =IF(OR(G19="",G19=0,H19=""),"",((H19-G19)/G19)*100) -> 0.79736211 | P19: Tata Tele | Q19: Invoice Sent | R19: Yes
A20: 17 | B20: 46203 | C20: TechsharingB | D20: PO-TBU-202627-07 | E20: Net New | F20: Business Standard (no Teams) (Annual - Monthly) | G20: 478.8 | H20: 486 | J20: {=_xlfn.LET(_xlpm.p,K20,IF(OR(_xlpm.p="",_xlpm.p="-",ISERROR(SEARCH("to",_xlpm.p))),"-",IFERROR(_xlfn.LET(_xlpm.s,TRIM(_xlfn.TEXTBEFORE(_xlpm.p,"to")),_xlpm.e,TRIM(_xlfn.TEXTAFTER(_xlpm.p,"to")),_xlpm.sd,DATE(VALUE(_xlfn.TEXTAFTER(_xlpm.s,"/",-1)),VALUE(_xlfn.TEXTBEFORE(_xlfn.TEXTAFTER(_xlpm.s,"/"),"/")),VALUE(_xlfn.TEXTBEFORE(_xlpm.s,"/"))),_xlpm.ed,DATE(VALUE(_xlfn.TEXTAFTER(_xlpm.e,"/",-1)),VALUE(_xlfn.TEXTBEFORE(_xlfn.TEXTAFTER(_xlpm.e,"/"),"/")),VALUE(_xlfn.TEXTBEFORE(_xlpm.e,"/"))),_xlpm.ed-_xlpm.sd+1),"-")))} -> 31 | K20: 02/07/2026 to 01/08/2026 | L20: 5 | M20: =IF(OR(L20="",L20="-"),"-",IF(AND(ISNUMBER(I20),I20<>0),I20*L20,IF(ISNUMBER(H20),H20*L20,"-"))) -> 2430 | N20: =IF(OR(G20="",H20="",L20=""),"",(H20-G20)*L20) -> 36 | O20: =IF(OR(G20="",G20=0,H20=""),"",((H20-G20)/G20)*100) -> 1.5037594 | P20: Redington | Q20: Invoice Sent | R20: No | S20: Invoice need to be send every month till July -2027 as its Annual commitment and monthly billing
A21: 18 | B21: 46204 | C21: Shreenaths Sustainables Pvt Ltd | E21: Prorate | F21: Business Basic (Annual - Annual ) | G21: 1336.32 | H21: 1385 | I21: 823.41096 | J21: {=_xlfn.LET(_xlpm.p,K21,IF(OR(_xlpm.p="",_xlpm.p="-",ISERROR(SEARCH("to",_xlpm.p))),"-",IFERROR(_xlfn.LET(_xlpm.s,TRIM(_xlfn.TEXTBEFORE(_xlpm.p,"to")),_xlpm.e,TRIM(_xlfn.TEXTAFTER(_xlpm.p,"to")),_xlpm.sd,DATE(VALUE(_xlfn.TEXTAFTER(_xlpm.s,"/",-1)),VALUE(_xlfn.TEXTBEFORE(_xlfn.TEXTAFTER(_xlpm.s,"/"),"/")),VALUE(_xlfn.TEXTBEFORE(_xlpm.s,"/"))),_xlpm.ed,DATE(VALUE(_xlfn.TEXTAFTER(_xlpm.e,"/",-1)),VALUE(_xlfn.TEXTBEFORE(_xlfn.TEXTAFTER(_xlpm.e,"/"),"/")),VALUE(_xlfn.TEXTBEFORE(_xlpm.e,"/"))),_xlpm.ed-_xlpm.sd+1),"-")))} -> 216 | K21: 1/7/2026 to 1/2/2027 | L21: 2 | M21: =IF(OR(L21="",L21="-"),"-",IF(AND(ISNUMBER(I21),I21<>0),I21*L21,IF(ISNUMBER(H21),H21*L21,"-"))) -> 1646.8219 | N21: =IF(OR(G21="",H21="",L21=""),"",(H21-G21)*L21) -> 97.36 | O21: =IF(OR(G21="",G21=0,H21=""),"",((H21-G21)/G21)*100) -> 3.64284 | P21: SoftwareOne | Q21: Invoice Sent | R21: No
A22: 19 | B22: 46216 | C22: Cloudwave Technologies Pvt Ltd | D22: PO-1017 | E22: Net New | F22: Business Basic (Annual - Annual ) | G22: 1583.04 | H22: 1600 | I22: - | J22: {=_xlfn.LET(_xlpm.p,K22,IF(OR(_xlpm.p="",_xlpm.p="-",ISERROR(SEARCH("to",_xlpm.p))),"-",IFERROR(_xlfn.LET(_xlpm.s,TRIM(_xlfn.TEXTBEFORE(_xlpm.p,"to")),_xlpm.e,TRIM(_xlfn.TEXTAFTER(_xlpm.p,"to")),_xlpm.sd,DATE(VALUE(_xlfn.TEXTAFTER(_xlpm.s,"/",-1)),VALUE(_xlfn.TEXTBEFORE(_xlfn.TEXTAFTER(_xlpm.s,"/"),"/")),VALUE(_xlfn.TEXTBEFORE(_xlpm.s,"/"))),_xlpm.ed,DATE(VALUE(_xlfn.TEXTAFTER(_xlpm.e,"/",-1)),VALUE(_xlfn.TEXTBEFORE(_xlfn.TEXTAFTER(_xlpm.e,"/"),"/")),VALUE(_xlfn.TEXTBEFORE(_xlpm.e,"/"))),_xlpm.ed-_xlpm.sd+1),"-")))} -> 365 | K22: 13/07/2026 to 12/07/2027 | L22: 120 | M22: =L22*H22 -> 192000 | N22: =IF(OR(G22="",H22="",L22=""),"",(H22-G22)*L22) -> 2035.2 | O22: 1 | P22: Redington | Q22: Invoice Sent | R22: No | S22: 50% of Invoice Received
A23: 20 | B23: 46216 | C23: Cloudwave Technologies Pvt Ltd | D23: PO-1017 | E23: Net New | F23: Exchange Online Plan 2 (Annual - Annual) | G23: 6384 | H23: 6447.84 | I23: - | J23: {=_xlfn.LET(_xlpm.p,K23,IF(OR(_xlpm.p="",_xlpm.p="-",ISERROR(SEARCH("to",_xlpm.p))),"-",IFERROR(_xlfn.LET(_xlpm.s,TRIM(_xlfn.TEXTBEFORE(_xlpm.p,"to")),_xlpm.e,TRIM(_xlfn.TEXTAFTER(_xlpm.p,"to")),_xlpm.sd,DATE(VALUE(_xlfn.TEXTAFTER(_xlpm.s,"/",-1)),VALUE(_xlfn.TEXTBEFORE(_xlfn.TEXTAFTER(_xlpm.s,"/"),"/")),VALUE(_xlfn.TEXTBEFORE(_xlpm.s,"/"))),_xlpm.ed,DATE(VALUE(_xlfn.TEXTAFTER(_xlpm.e,"/",-1)),VALUE(_xlfn.TEXTBEFORE(_xlfn.TEXTAFTER(_xlpm.e,"/"),"/")),VALUE(_xlfn.TEXTBEFORE(_xlpm.e,"/"))),_xlpm.ed-_xlpm.sd+1),"-")))} -> 365 | K23: 13/07/2026 to 12/07/2027 | L23: 8 | M23: =L23*H23 -> 51582.72 | N23: =IF(OR(G23="",H23="",L23=""),"",(H23-G23)*L23) -> 510.72 | O23: 1 | P23: Redington | Q23: Invoice Sent | R23: No
A24: 21 | B24: 46226 | C24: NuGRP Solutions LLP | E24: Net New | F24: Business Basic (Annual - Annual ) | G24: 1599.4 | H24: 1640.2 | I24: - | J24: {=_xlfn.LET(_xlpm.p,K24,IF(OR(_xlpm.p="",_xlpm.p="-",ISERROR(SEARCH("to",_xlpm.p))),"-",IFERROR(_xlfn.LET(_xlpm.s,TRIM(_xlfn.TEXTBEFORE(_xlpm.p,"to")),_xlpm.e,TRIM(_xlfn.TEXTAFTER(_xlpm.p,"to")),_xlpm.sd,DATE(VALUE(_xlfn.TEXTAFTER(_xlpm.s,"/",-1)),VALUE(_xlfn.TEXTBEFORE(_xlfn.TEXTAFTER(_xlpm.s,"/"),"/")),VALUE(_xlfn.TEXTBEFORE(_xlpm.s,"/"))),_xlpm.ed,DATE(VALUE(_xlfn.TEXTAFTER(_xlpm.e,"/",-1)),VALUE(_xlfn.TEXTBEFORE(_xlfn.TEXTAFTER(_xlpm.e,"/"),"/")),VALUE(_xlfn.TEXTBEFORE(_xlpm.e,"/"))),_xlpm.ed-_xlpm.sd+1),"-")))} -> 365 | K24: 23/07/2026 to 22/07/2027 | L24: 5 | M24: =IF(OR(L24="",L24="-"),"-",IF(AND(ISNUMBER(I24),I24<>0),I24*L24,IF(ISNUMBER(H24),H24*L24,"-"))) -> 8201 | N24: =IF(OR(G24="",H24="",L24=""),"",(H24-G24)*L24) -> 204 | O24: 2.5 | P24: Redington | Q24: Need to send invoice | R24: No | S24: Need to bill on 1st Sep
E25: Net New | F25: Business Standard (Annual - Annual) | G25: 8090.88 | H25: 8297.3 | I25: - | J25: {=_xlfn.LET(_xlpm.p,K25,IF(OR(_xlpm.p="",_xlpm.p="-",ISERROR(SEARCH("to",_xlpm.p))),"-",IFERROR(_xlfn.LET(_xlpm.s,TRIM(_xlfn.TEXTBEFORE(_xlpm.p,"to")),_xlpm.e,TRIM(_xlfn.TEXTAFTER(_xlpm.p,"to")),_xlpm.sd,DATE(VALUE(_xlfn.TEXTAFTER(_xlpm.s,"/",-1)),VALUE(_xlfn.TEXTBEFORE(_xlfn.TEXTAFTER(_xlpm.s,"/"),"/")),VALUE(_xlfn.TEXTBEFORE(_xlpm.s,"/"))),_xlpm.ed,DATE(VALUE(_xlfn.TEXTAFTER(_xlpm.e,"/",-1)),VALUE(_xlfn.TEXTBEFORE(_xlfn.TEXTAFTER(_xlpm.e,"/"),"/")),VALUE(_xlfn.TEXTBEFORE(_xlpm.e,"/"))),_xlpm.ed-_xlpm.sd+1),"-")))} -> 365 | K25: 23/07/2026 to 22/07/2027 | L25: 7 | M25: =IF(OR(L25="",L25="-"),"-",IF(AND(ISNUMBER(I25),I25<>0),I25*L25,IF(ISNUMBER(H25),H25*L25,"-"))) -> 58081.1 | N25: =IF(OR(G25="",H25="",L25=""),"",(H25-G25)*L25) -> 1444.94 | O25: 2.5 | P25: Redington | Q25: Need to send invoice | R25: No | S25: Need to bill on 1st Sep
E26: - | F26: Exchange Migration Activity (One-Time) | G26: 0 | H26: 300 | I26: - | J26: {=_xlfn.LET(_xlpm.p,K26,IF(OR(_xlpm.p="",_xlpm.p="-",ISERROR(SEARCH("to",_xlpm.p))),"-",IFERROR(_xlfn.LET(_xlpm.s,TRIM(_xlfn.TEXTBEFORE(_xlpm.p,"to")),_xlpm.e,TRIM(_xlfn.TEXTAFTER(_xlpm.p,"to")),_xlpm.sd,DATE(VALUE(_xlfn.TEXTAFTER(_xlpm.s,"/",-1)),VALUE(_xlfn.TEXTBEFORE(_xlfn.TEXTAFTER(_xlpm.s,"/"),"/")),VALUE(_xlfn.TEXTBEFORE(_xlpm.s,"/"))),_xlpm.ed,DATE(VALUE(_xlfn.TEXTAFTER(_xlpm.e,"/",-1)),VALUE(_xlfn.TEXTBEFORE(_xlfn.TEXTAFTER(_xlpm.e,"/"),"/")),VALUE(_xlfn.TEXTBEFORE(_xlpm.e,"/"))),_xlpm.ed-_xlpm.sd+1),"-")))} -> - | K26: - | L26: 12 | M26: =IF(OR(L26="",L26="-"),"-",IF(AND(ISNUMBER(I26),I26<>0),I26*L26,IF(ISNUMBER(H26),H26*L26,"-"))) -> 3600 | N26: =IF(OR(G26="",H26="",L26=""),"",(H26-G26)*L26) -> 3600 | O26: - | Q26: Need to send invoice | R26: No | S26: Need to bill on 1st Sep
A27: 22 | B27: 46230 | C27: Neo TVS | E27: Net New | F27: Business Basic (Annual - Annual ) | G27: 1591.2 | H27: 1670.8 | I27: - | J27: {=_xlfn.LET(_xlpm.p,K27,IF(OR(_xlpm.p="",_xlpm.p="-",ISERROR(SEARCH("to",_xlpm.p))),"-",IFERROR(_xlfn.LET(_xlpm.s,TRIM(_xlfn.TEXTBEFORE(_xlpm.p,"to")),_xlpm.e,TRIM(_xlfn.TEXTAFTER(_xlpm.p,"to")),_xlpm.sd,DATE(VALUE(_xlfn.TEXTAFTER(_xlpm.s,"/",-1)),VALUE(_xlfn.TEXTBEFORE(_xlfn.TEXTAFTER(_xlpm.s,"/"),"/")),VALUE(_xlfn.TEXTBEFORE(_xlpm.s,"/"))),_xlpm.ed,DATE(VALUE(_xlfn.TEXTAFTER(_xlpm.e,"/",-1)),VALUE(_xlfn.TEXTBEFORE(_xlfn.TEXTAFTER(_xlpm.e,"/"),"/")),VALUE(_xlfn.TEXTBEFORE(_xlpm.e,"/"))),_xlpm.ed-_xlpm.sd+1),"-")))} -> 365 | K27: 27/07/2026 to 26/07/2027 | L27: 16 | M27: =IF(OR(L27="",L27="-"),"-",IF(AND(ISNUMBER(I27),I27<>0),I27*L27,IF(ISNUMBER(H27),H27*L27,"-"))) -> 26732.8 | N27: =IF(OR(G27="",H27="",L27=""),"",(H27-G27)*L27) -> 1273.6 | O27: 2.5 | P27: Redington | Q27: Invoice Sent | R27: No
A28: 23 | B28: 46230 | C28: ER Brains IT Solutions | E28: Net New | F28: D365 Business Central Premium (Annual - Monthly) | G28: 81736.013 | H28: 84030.99 | J28: {=_xlfn.LET(_xlpm.p,K28,IF(OR(_xlpm.p="",_xlpm.p="-",ISERROR(SEARCH("to",_xlpm.p))),"-",IFERROR(_xlfn.LET(_xlpm.s,TRIM(_xlfn.TEXTBEFORE(_xlpm.p,"to")),_xlpm.e,TRIM(_xlfn.TEXTAFTER(_xlpm.p,"to")),_xlpm.sd,DATE(VALUE(_xlfn.TEXTAFTER(_xlpm.s,"/",-1)),VALUE(_xlfn.TEXTBEFORE(_xlfn.TEXTAFTER(_xlpm.s,"/"),"/")),VALUE(_xlfn.TEXTBEFORE(_xlpm.s,"/"))),_xlpm.ed,DATE(VALUE(_xlfn.TEXTAFTER(_xlpm.e,"/",-1)),VALUE(_xlfn.TEXTBEFORE(_xlfn.TEXTAFTER(_xlpm.e,"/"),"/")),VALUE(_xlfn.TEXTBEFORE(_xlpm.e,"/"))),_xlpm.ed-_xlpm.sd+1),"-")))} -> 365 | K28: 27/07/2026 to 26/07/2027 | L28: 1 | M28: =IF(OR(L28="",L28="-"),"-",IF(AND(ISNUMBER(I28),I28<>0),I28*L28,IF(ISNUMBER(H28),H28*L28,"-"))) -> 84030.99 | N28: =IF(OR(G28="",H28="",L28=""),"",(H28-G28)*L28) -> 2294.9772 | O28: 2.81 | P28: SoftwareOne | Q28: Invoice Sent | R28: No | S28: Invoice need to be send every month till July -2027 as its Annual commitment and monthly billing (Bill for 7002.5 every month for 1 year)
A29: 24 | B29: 46232 | C29: GRP Solutions | E29: Net New | F29: Windows Server 2025 Datacenter - 16 Core - Edu | G29: 122669 | H29: 124509 | J29: {=_xlfn.LET(_xlpm.p,K29,IF(OR(_xlpm.p="",_xlpm.p="-",ISERROR(SEARCH("to",_xlpm.p))),"-",IFERROR(_xlfn.LET(_xlpm.s,TRIM(_xlfn.TEXTBEFORE(_xlpm.p,"to")),_xlpm.e,TRIM(_xlfn.TEXTAFTER(_xlpm.p,"to")),_xlpm.sd,DATE(VALUE(_xlfn.TEXTAFTER(_xlpm.s,"/",-1)),VALUE(_xlfn.TEXTBEFORE(_xlfn.TEXTAFTER(_xlpm.s,"/"),"/")),VALUE(_xlfn.TEXTBEFORE(_xlpm.s,"/"))),_xlpm.ed,DATE(VALUE(_xlfn.TEXTAFTER(_xlpm.e,"/",-1)),VALUE(_xlfn.TEXTBEFORE(_xlfn.TEXTAFTER(_xlpm.e,"/"),"/")),VALUE(_xlfn.TEXTBEFORE(_xlpm.e,"/"))),_xlpm.ed-_xlpm.sd+1),"-")))} -> - | K29: Perpetual | L29: 1 | M29: =IF(OR(L29="",L29="-"),"-",IF(AND(ISNUMBER(I29),I29<>0),I29*L29,IF(ISNUMBER(H29),H29*L29,"-"))) -> 124509 | N29: =IF(OR(G29="",H29="",L29=""),"",(H29-G29)*L29) -> 1840 | O29: 1.5 | P29: Tata Tele | Q29: Invoice Sent | R29: Yes
E30: Net New | F30: Windows Server 2025 Standard - 16 Core - Edu | G30: 21308 | H30: 21627 | J30: {=_xlfn.LET(_xlpm.p,K30,IF(OR(_xlpm.p="",_xlpm.p="-",ISERROR(SEARCH("to",_xlpm.p))),"-",IFERROR(_xlfn.LET(_xlpm.s,TRIM(_xlfn.TEXTBEFORE(_xlpm.p,"to")),_xlpm.e,TRIM(_xlfn.TEXTAFTER(_xlpm.p,"to")),_xlpm.sd,DATE(VALUE(_xlfn.TEXTAFTER(_xlpm.s,"/",-1)),VALUE(_xlfn.TEXTBEFORE(_xlfn.TEXTAFTER(_xlpm.s,"/"),"/")),VALUE(_xlfn.TEXTBEFORE(_xlpm.s,"/"))),_xlpm.ed,DATE(VALUE(_xlfn.TEXTAFTER(_xlpm.e,"/",-1)),VALUE(_xlfn.TEXTBEFORE(_xlfn.TEXTAFTER(_xlpm.e,"/"),"/")),VALUE(_xlfn.TEXTBEFORE(_xlpm.e,"/"))),_xlpm.ed-_xlpm.sd+1),"-")))} -> - | K30: Perpetual | L30: 3 | M30: =IF(OR(L30="",L30="-"),"-",IF(AND(ISNUMBER(I30),I30<>0),I30*L30,IF(ISNUMBER(H30),H30*L30,"-"))) -> 64881 | N30: =IF(OR(G30="",H30="",L30=""),"",(H30-G30)*L30) -> 957 | O30: 1.5 | P30: Tata Tele
E31: Net New | F31: SQL Server 2025 Standard Core - 2 Core - Edu | G31: 71584.5 | H31: 72658 | J31: {=_xlfn.LET(_xlpm.p,K31,IF(OR(_xlpm.p="",_xlpm.p="-",ISERROR(SEARCH("to",_xlpm.p))),"-",IFERROR(_xlfn.LET(_xlpm.s,TRIM(_xlfn.TEXTBEFORE(_xlpm.p,"to")),_xlpm.e,TRIM(_xlfn.TEXTAFTER(_xlpm.p,"to")),_xlpm.sd,DATE(VALUE(_xlfn.TEXTAFTER(_xlpm.s,"/",-1)),VALUE(_xlfn.TEXTBEFORE(_xlfn.TEXTAFTER(_xlpm.s,"/"),"/")),VALUE(_xlfn.TEXTBEFORE(_xlpm.s,"/"))),_xlpm.ed,DATE(VALUE(_xlfn.TEXTAFTER(_xlpm.e,"/",-1)),VALUE(_xlfn.TEXTBEFORE(_xlfn.TEXTAFTER(_xlpm.e,"/"),"/")),VALUE(_xlfn.TEXTBEFORE(_xlpm.e,"/"))),_xlpm.ed-_xlpm.sd+1),"-")))} -> - | K31: Prepetual | L31: 2 | M31: =IF(OR(L31="",L31="-"),"-",IF(AND(ISNUMBER(I31),I31<>0),I31*L31,IF(ISNUMBER(H31),H31*L31,"-"))) -> 145316 | N31: =IF(OR(G31="",H31="",L31=""),"",(H31-G31)*L31) -> 2147 | O31: 1.5 | P31: Tata Tele
A32: 25 | B32: 46239 | C32: NexGen Robotics Automation | E32: Renewal | F32: Business Basic (Annual - Annual ) | G32: 1574.88 | H32: 1623.84 | J32: {=_xlfn.LET(_xlpm.p,K32,IF(OR(_xlpm.p="",_xlpm.p="-",ISERROR(SEARCH("to",_xlpm.p))),"-",IFERROR(_xlfn.LET(_xlpm.s,TRIM(_xlfn.TEXTBEFORE(_xlpm.p,"to")),_xlpm.e,TRIM(_xlfn.TEXTAFTER(_xlpm.p,"to")),_xlpm.sd,DATE(VALUE(_xlfn.TEXTAFTER(_xlpm.s,"/",-1)),VALUE(_xlfn.TEXTBEFORE(_xlfn.TEXTAFTER(_xlpm.s,"/"),"/")),VALUE(_xlfn.TEXTBEFORE(_xlpm.s,"/"))),_xlpm.ed,DATE(VALUE(_xlfn.TEXTAFTER(_xlpm.e,"/",-1)),VALUE(_xlfn.TEXTBEFORE(_xlfn.TEXTAFTER(_xlpm.e,"/"),"/")),VALUE(_xlfn.TEXTBEFORE(_xlpm.e,"/"))),_xlpm.ed-_xlpm.sd+1),"-")))} -> 365 | K32: 05/08/2026 to 04/08/2027 | L32: 15 | M32: =IF(OR(L32="",L32="-"),"-",IF(AND(ISNUMBER(I32),I32<>0),I32*L32,IF(ISNUMBER(H32),H32*L32,"-"))) -> 24357.6 | N32: =IF(OR(G32="",H32="",L32=""),"",(H32-G32)*L32) -> 734.4 | O32: 2 | P32: SoftwareOne | Q32: Invoice Sent | R32: No
A33: 26 | B33: 46239 | C33: Whitepaper Solutions | E33: Renewal | F33: Business Basic (Annual - Annual ) | G33: 1574.88 | H33: 1664.6 | J33: {=_xlfn.LET(_xlpm.p,K33,IF(OR(_xlpm.p="",_xlpm.p="-",ISERROR(SEARCH("to",_xlpm.p))),"-",IFERROR(_xlfn.LET(_xlpm.s,TRIM(_xlfn.TEXTBEFORE(_xlpm.p,"to")),_xlpm.e,TRIM(_xlfn.TEXTAFTER(_xlpm.p,"to")),_xlpm.sd,DATE(VALUE(_xlfn.TEXTAFTER(_xlpm.s,"/",-1)),VALUE(_xlfn.TEXTBEFORE(_xlfn.TEXTAFTER(_xlpm.s,"/"),"/")),VALUE(_xlfn.TEXTBEFORE(_xlpm.s,"/"))),_xlpm.ed,DATE(VALUE(_xlfn.TEXTAFTER(_xlpm.e,"/",-1)),VALUE(_xlfn.TEXTBEFORE(_xlfn.TEXTAFTER(_xlpm.e,"/"),"/")),VALUE(_xlfn.TEXTBEFORE(_xlpm.e,"/"))),_xlpm.ed-_xlpm.sd+1),"-")))} -> 365 | K33: 05/08/2026 to 04/08/2027 | L33: 20 | M33: =IF(OR(L33="",L33="-"),"-",IF(AND(ISNUMBER(I33),I33<>0),I33*L33,IF(ISNUMBER(H33),H33*L33,"-"))) -> 33292 | N33: =IF(OR(G33="",H33="",L33=""),"",(H33-G33)*L33) -> 1794.4 | O33: 5.7 | P33: SoftwareOne | Q33: Invoice Sent | R33: No
A34: 27 | B34: 46240 | C34: CNC India | E34: Renewal | F34: Business Basic (Annual - Annual ) | G34: 1574.88 | H34: 1599.36 | J34: {=_xlfn.LET(_xlpm.p,K34,IF(OR(_xlpm.p="",_xlpm.p="-",ISERROR(SEARCH("to",_xlpm.p))),"-",IFERROR(_xlfn.LET(_xlpm.s,TRIM(_xlfn.TEXTBEFORE(_xlpm.p,"to")),_xlpm.e,TRIM(_xlfn.TEXTAFTER(_xlpm.p,"to")),_xlpm.sd,DATE(VALUE(_xlfn.TEXTAFTER(_xlpm.s,"/",-1)),VALUE(_xlfn.TEXTBEFORE(_xlfn.TEXTAFTER(_xlpm.s,"/"),"/")),VALUE(_xlfn.TEXTBEFORE(_xlpm.s,"/"))),_xlpm.ed,DATE(VALUE(_xlfn.TEXTAFTER(_xlpm.e,"/",-1)),VALUE(_xlfn.TEXTBEFORE(_xlfn.TEXTAFTER(_xlpm.e,"/"),"/")),VALUE(_xlfn.TEXTBEFORE(_xlpm.e,"/"))),_xlpm.ed-_xlpm.sd+1),"-")))} -> 365 | K34: 06/08/2026 to 05/08/2027 | L34: 190 | M34: =IF(OR(L34="",L34="-"),"-",IF(AND(ISNUMBER(I34),I34<>0),I34*L34,IF(ISNUMBER(H34),H34*L34,"-"))) -> 303878.4 | N34: =IF(OR(G34="",H34="",L34=""),"",(H34-G34)*L34) -> 4651.2 | O34: 1.5 | P34: SoftwareOne | Q34: Invoice Sent | R34: No
A35: 28 | B35: 46241 | C35: GRP Solutions | E35: Renewal | F35: Business Basic (Annual - Annual ) | G35: 1574.88 | H35: 1640.2 | J35: {=_xlfn.LET(_xlpm.p,K35,IF(OR(_xlpm.p="",_xlpm.p="-",ISERROR(SEARCH("to",_xlpm.p))),"-",IFERROR(_xlfn.LET(_xlpm.s,TRIM(_xlfn.TEXTBEFORE(_xlpm.p,"to")),_xlpm.e,TRIM(_xlfn.TEXTAFTER(_xlpm.p,"to")),_xlpm.sd,DATE(VALUE(_xlfn.TEXTAFTER(_xlpm.s,"/",-1)),VALUE(_xlfn.TEXTBEFORE(_xlfn.TEXTAFTER(_xlpm.s,"/"),"/")),VALUE(_xlfn.TEXTBEFORE(_xlpm.s,"/"))),_xlpm.ed,DATE(VALUE(_xlfn.TEXTAFTER(_xlpm.e,"/",-1)),VALUE(_xlfn.TEXTBEFORE(_xlfn.TEXTAFTER(_xlpm.e,"/"),"/")),VALUE(_xlfn.TEXTBEFORE(_xlpm.e,"/"))),_xlpm.ed-_xlpm.sd+1),"-")))} -> 365 | K35: 07/08/2026 to 06/08/2027 | L35: 2 | M35: =IF(OR(L35="",L35="-"),"-",IF(AND(ISNUMBER(I35),I35<>0),I35*L35,IF(ISNUMBER(H35),H35*L35,"-"))) -> 3280.4 | N35: =IF(OR(G35="",H35="",L35=""),"",(H35-G35)*L35) -> 130.64 | O35: 4 | P35: SoftwareOne | Q35: Need to send invoice | R35: No | S35: Need to send invoice on 1st Sep
E36: Renewal | F36: Business Standard (Annual - Annual) | G36: 7967.04 | H36: 8297.3 | J36: {=_xlfn.LET(_xlpm.p,K36,IF(OR(_xlpm.p="",_xlpm.p="-",ISERROR(SEARCH("to",_xlpm.p))),"-",IFERROR(_xlfn.LET(_xlpm.s,TRIM(_xlfn.TEXTBEFORE(_xlpm.p,"to")),_xlpm.e,TRIM(_xlfn.TEXTAFTER(_xlpm.p,"to")),_xlpm.sd,DATE(VALUE(_xlfn.TEXTAFTER(_xlpm.s,"/",-1)),VALUE(_xlfn.TEXTBEFORE(_xlfn.TEXTAFTER(_xlpm.s,"/"),"/")),VALUE(_xlfn.TEXTBEFORE(_xlpm.s,"/"))),_xlpm.ed,DATE(VALUE(_xlfn.TEXTAFTER(_xlpm.e,"/",-1)),VALUE(_xlfn.TEXTBEFORE(_xlfn.TEXTAFTER(_xlpm.e,"/"),"/")),VALUE(_xlfn.TEXTBEFORE(_xlpm.e,"/"))),_xlpm.ed-_xlpm.sd+1),"-")))} -> 365 | K36: 07/08/2026 to 06/08/2027 | L36: 11 | M36: =IF(OR(L36="",L36="-"),"-",IF(AND(ISNUMBER(I36),I36<>0),I36*L36,IF(ISNUMBER(H36),H36*L36,"-"))) -> 91270.3 | N36: =IF(OR(G36="",H36="",L36=""),"",(H36-G36)*L36) -> 3632.86 | O36: 4 | P36: SoftwareOne | S36: Need to send invoice on 1st Sep
A37: 29 | B37: 46241 | C37: NuGRP Solutions LLP | E37: Renewal | F37: Business Basic (Monthly - Monthly ) | G37: 165 | H37: 170 | J37: {=_xlfn.LET(_xlpm.p,K37,IF(OR(_xlpm.p="",_xlpm.p="-",ISERROR(SEARCH("to",_xlpm.p))),"-",IFERROR(_xlfn.LET(_xlpm.s,TRIM(_xlfn.TEXTBEFORE(_xlpm.p,"to")),_xlpm.e,TRIM(_xlfn.TEXTAFTER(_xlpm.p,"to")),_xlpm.sd,DATE(VALUE(_xlfn.TEXTAFTER(_xlpm.s,"/",-1)),VALUE(_xlfn.TEXTBEFORE(_xlfn.TEXTAFTER(_xlpm.s,"/"),"/")),VALUE(_xlfn.TEXTBEFORE(_xlpm.s,"/"))),_xlpm.ed,DATE(VALUE(_xlfn.TEXTAFTER(_xlpm.e,"/",-1)),VALUE(_xlfn.TEXTBEFORE(_xlfn.TEXTAFTER(_xlpm.e,"/"),"/")),VALUE(_xlfn.TEXTBEFORE(_xlpm.e,"/"))),_xlpm.ed-_xlpm.sd+1),"-")))} -> 365 | K37: 07/08/2026 to 06/08/2027 | L37: 2 | M37: =IF(OR(L37="",L37="-"),"-",IF(AND(ISNUMBER(I37),I37<>0),I37*L37,IF(ISNUMBER(H37),H37*L37,"-"))) -> 340 | N37: =IF(OR(G37="",H37="",L37=""),"",(H37-G37)*L37) -> 10 | O37: 3.5 | P37: SoftwareOne | Q37: Need to send invoice | R37: No | S37: Need to send invoice on 1st Sep
E38: Renewal | F38: Business Basic (Annual - Annual ) | G38: 1574.88 | H38: 1640.2 | J38: {=_xlfn.LET(_xlpm.p,K38,IF(OR(_xlpm.p="",_xlpm.p="-",ISERROR(SEARCH("to",_xlpm.p))),"-",IFERROR(_xlfn.LET(_xlpm.s,TRIM(_xlfn.TEXTBEFORE(_xlpm.p,"to")),_xlpm.e,TRIM(_xlfn.TEXTAFTER(_xlpm.p,"to")),_xlpm.sd,DATE(VALUE(_xlfn.TEXTAFTER(_xlpm.s,"/",-1)),VALUE(_xlfn.TEXTBEFORE(_xlfn.TEXTAFTER(_xlpm.s,"/"),"/")),VALUE(_xlfn.TEXTBEFORE(_xlpm.s,"/"))),_xlpm.ed,DATE(VALUE(_xlfn.TEXTAFTER(_xlpm.e,"/",-1)),VALUE(_xlfn.TEXTBEFORE(_xlfn.TEXTAFTER(_xlpm.e,"/"),"/")),VALUE(_xlfn.TEXTBEFORE(_xlpm.e,"/"))),_xlpm.ed-_xlpm.sd+1),"-")))} -> 365 | K38: 07/08/2026 to 06/08/2027 | L38: 3 | M38: =IF(OR(L38="",L38="-"),"-",IF(AND(ISNUMBER(I38),I38<>0),I38*L38,IF(ISNUMBER(H38),H38*L38,"-"))) -> 4920.6 | N38: =IF(OR(G38="",H38="",L38=""),"",(H38-G38)*L38) -> 195.96 | O38: 4 | P38: SoftwareOne | S38: Need to send invoice on 1st Sep
A39: 30 | B39: 46244 | C39: NuGRP Solutions LLP | E39: Net New | F39: SQL Server 2025 Standard edition Perpetual 1 Server License | G39: 71694 | H39: 73127 | J39: {=_xlfn.LET(_xlpm.p,K39,IF(OR(_xlpm.p="",_xlpm.p="-",ISERROR(SEARCH("to",_xlpm.p))),"-",IFERROR(_xlfn.LET(_xlpm.s,TRIM(_xlfn.TEXTBEFORE(_xlpm.p,"to")),_xlpm.e,TRIM(_xlfn.TEXTAFTER(_xlpm.p,"to")),_xlpm.sd,DATE(VALUE(_xlfn.TEXTAFTER(_xlpm.s,"/",-1)),VALUE(_xlfn.TEXTBEFORE(_xlfn.TEXTAFTER(_xlpm.s,"/"),"/")),VALUE(_xlfn.TEXTBEFORE(_xlpm.s,"/"))),_xlpm.ed,DATE(VALUE(_xlfn.TEXTAFTER(_xlpm.e,"/",-1)),VALUE(_xlfn.TEXTBEFORE(_xlfn.TEXTAFTER(_xlpm.e,"/"),"/")),VALUE(_xlfn.TEXTBEFORE(_xlpm.e,"/"))),_xlpm.ed-_xlpm.sd+1),"-")))} -> - | K39: Prepetual | L39: 2 | M39: =IF(OR(L39="",L39="-"),"-",IF(AND(ISNUMBER(I39),I39<>0),I39*L39,IF(ISNUMBER(H39),H39*L39,"-"))) -> 146254 | N39: =IF(OR(G39="",H39="",L39=""),"",(H39-G39)*L39) -> 2866 | O39: 2 | P39: Tata Tele | Q39: Invoice Sent | R39: No
A40: 31 | B40: 46244 | C40: Krisam Automation Pvt Ltd | E40: Renewal | F40: Business Basic (Annual - Annual ) | G40: 1599.36 | H40: 1615.35 | J40: {=_xlfn.LET(_xlpm.p,K40,IF(OR(_xlpm.p="",_xlpm.p="-",ISERROR(SEARCH("to",_xlpm.p))),"-",IFERROR(_xlfn.LET(_xlpm.s,TRIM(_xlfn.TEXTBEFORE(_xlpm.p,"to")),_xlpm.e,TRIM(_xlfn.TEXTAFTER(_xlpm.p,"to")),_xlpm.sd,DATE(VALUE(_xlfn.TEXTAFTER(_xlpm.s,"/",-1)),VALUE(_xlfn.TEXTBEFORE(_xlfn.TEXTAFTER(_xlpm.s,"/"),"/")),VALUE(_xlfn.TEXTBEFORE(_xlpm.s,"/"))),_xlpm.ed,DATE(VALUE(_xlfn.TEXTAFTER(_xlpm.e,"/",-1)),VALUE(_xlfn.TEXTBEFORE(_xlfn.TEXTAFTER(_xlpm.e,"/"),"/")),VALUE(_xlfn.TEXTBEFORE(_xlpm.e,"/"))),_xlpm.ed-_xlpm.sd+1),"-")))} -> 365 | K40: 10/08/2026 to 09/08/2027 | L40: 65 | M40: =IF(OR(L40="",L40="-"),"-",IF(AND(ISNUMBER(I40),I40<>0),I40*L40,IF(ISNUMBER(H40),H40*L40,"-"))) -> 104997.75 | N40: =IF(OR(G40="",H40="",L40=""),"",(H40-G40)*L40) -> 1039.35 | O40: 1 | P40: Redington | Q40: Invoice Sent | R40: No
A41: 32 | B41: 46245 | C41: Shreenaths Renewables Pvt Ltd | E41: Net New | F41: Business Basic (Annual - Annual ) | G41: 1574.88 | H41: 1640.2 | J41: {=_xlfn.LET(_xlpm.p,K41,IF(OR(_xlpm.p="",_xlpm.p="-",ISERROR(SEARCH("to",_xlpm.p))),"-",IFERROR(_xlfn.LET(_xlpm.s,TRIM(_xlfn.TEXTBEFORE(_xlpm.p,"to")),_xlpm.e,TRIM(_xlfn.TEXTAFTER(_xlpm.p,"to")),_xlpm.sd,DATE(VALUE(_xlfn.TEXTAFTER(_xlpm.s,"/",-1)),VALUE(_xlfn.TEXTBEFORE(_xlfn.TEXTAFTER(_xlpm.s,"/"),"/")),VALUE(_xlfn.TEXTBEFORE(_xlpm.s,"/"))),_xlpm.ed,DATE(VALUE(_xlfn.TEXTAFTER(_xlpm.e,"/",-1)),VALUE(_xlfn.TEXTBEFORE(_xlfn.TEXTAFTER(_xlpm.e,"/"),"/")),VALUE(_xlfn.TEXTBEFORE(_xlpm.e,"/"))),_xlpm.ed-_xlpm.sd+1),"-")))} -> 365 | K41: 11/08/2026 to 10/08/2027 | L41: 15 | M41: =IF(OR(L41="",L41="-"),"-",IF(AND(ISNUMBER(I41),I41<>0),I41*L41,IF(ISNUMBER(H41),H41*L41,"-"))) -> 24603 | N41: =IF(OR(G41="",H41="",L41=""),"",(H41-G41)*L41) -> 979.8 | O41: 4.15 | P41: SoftwareOne | Q41: Invoice Sent | R41: No
E42: - | F42: Exchange Migration Activity (One-Time) | G42: 0 | H42: 300 | J42: {=_xlfn.LET(_xlpm.p,K42,IF(OR(_xlpm.p="",_xlpm.p="-",ISERROR(SEARCH("to",_xlpm.p))),"-",IFERROR(_xlfn.LET(_xlpm.s,TRIM(_xlfn.TEXTBEFORE(_xlpm.p,"to")),_xlpm.e,TRIM(_xlfn.TEXTAFTER(_xlpm.p,"to")),_xlpm.sd,DATE(VALUE(_xlfn.TEXTAFTER(_xlpm.s,"/",-1)),VALUE(_xlfn.TEXTBEFORE(_xlfn.TEXTAFTER(_xlpm.s,"/"),"/")),VALUE(_xlfn.TEXTBEFORE(_xlpm.s,"/"))),_xlpm.ed,DATE(VALUE(_xlfn.TEXTAFTER(_xlpm.e,"/",-1)),VALUE(_xlfn.TEXTBEFORE(_xlfn.TEXTAFTER(_xlpm.e,"/"),"/")),VALUE(_xlfn.TEXTBEFORE(_xlpm.e,"/"))),_xlpm.ed-_xlpm.sd+1),"-")))} -> - | K42: - | L42: 15 | M42: =IF(OR(L42="",L42="-"),"-",IF(AND(ISNUMBER(I42),I42<>0),I42*L42,IF(ISNUMBER(H42),H42*L42,"-"))) -> 4500 | N42: =IF(OR(G42="",H42="",L42=""),"",(H42-G42)*L42) -> 4500 | O42: -
A43: 33 | B43: 46246 | C43: QL Partners | E43: Net New | F43: Business Standard (Annual - Annual) | G43: 8090.88 | H43: 8462 | J43: {=_xlfn.LET(_xlpm.p,K43,IF(OR(_xlpm.p="",_xlpm.p="-",ISERROR(SEARCH("to",_xlpm.p))),"-",IFERROR(_xlfn.LET(_xlpm.s,TRIM(_xlfn.TEXTBEFORE(_xlpm.p,"to")),_xlpm.e,TRIM(_xlfn.TEXTAFTER(_xlpm.p,"to")),_xlpm.sd,DATE(VALUE(_xlfn.TEXTAFTER(_xlpm.s,"/",-1)),VALUE(_xlfn.TEXTBEFORE(_xlfn.TEXTAFTER(_xlpm.s,"/"),"/")),VALUE(_xlfn.TEXTBEFORE(_xlpm.s,"/"))),_xlpm.ed,DATE(VALUE(_xlfn.TEXTAFTER(_xlpm.e,"/",-1)),VALUE(_xlfn.TEXTBEFORE(_xlfn.TEXTAFTER(_xlpm.e,"/"),"/")),VALUE(_xlfn.TEXTBEFORE(_xlpm.e,"/"))),_xlpm.ed-_xlpm.sd+1),"-")))} -> 365 | K43: 12/08/2026 to 11/08/2027 | L43: 25 | M43: =IF(OR(L43="",L43="-"),"-",IF(AND(ISNUMBER(I43),I43<>0),I43*L43,IF(ISNUMBER(H43),H43*L43,"-"))) -> 211550 | N43: =IF(OR(G43="",H43="",L43=""),"",(H43-G43)*L43) -> 9278 | O43: =IF(OR(G43="",G43=0,H43=""),"",((H43-G43)/G43)*100) -> 4.5868929 | P43: Redington | Q43: Invoice Sent | R43: No
F44: Exchange Migration Activity (One-Time) | G44: 0 | H44: 350 | J44: {=_xlfn.LET(_xlpm.p,K44,IF(OR(_xlpm.p="",_xlpm.p="-",ISERROR(SEARCH("to",_xlpm.p))),"-",IFERROR(_xlfn.LET(_xlpm.s,TRIM(_xlfn.TEXTBEFORE(_xlpm.p,"to")),_xlpm.e,TRIM(_xlfn.TEXTAFTER(_xlpm.p,"to")),_xlpm.sd,DATE(VALUE(_xlfn.TEXTAFTER(_xlpm.s,"/",-1)),VALUE(_xlfn.TEXTBEFORE(_xlfn.TEXTAFTER(_xlpm.s,"/"),"/")),VALUE(_xlfn.TEXTBEFORE(_xlpm.s,"/"))),_xlpm.ed,DATE(VALUE(_xlfn.TEXTAFTER(_xlpm.e,"/",-1)),VALUE(_xlfn.TEXTBEFORE(_xlfn.TEXTAFTER(_xlpm.e,"/"),"/")),VALUE(_xlfn.TEXTBEFORE(_xlpm.e,"/"))),_xlpm.ed-_xlpm.sd+1),"-")))} -> - | K44: - | L44: 20 | M44: =IF(OR(L44="",L44="-"),"-",IF(AND(ISNUMBER(I44),I44<>0),I44*L44,IF(ISNUMBER(H44),H44*L44,"-"))) -> 7000 | N44: =IF(OR(G44="",H44="",L44=""),"",(H44-G44)*L44) -> 7000 | O44: -
A45: =ROW() - ROW($A$2) -> 43 | B45: 46246 | C45: AJM CNC Tool Tech | E45: Prorate | F45: Business Basic (Annual - Annual ) | G45: 1343.28 | H45: 1392 | I45: 118.22 | J45: {=_xlfn.LET(_xlpm.p,K45,IF(OR(_xlpm.p="",_xlpm.p="-",ISERROR(SEARCH("to",_xlpm.p))),"-",IFERROR(_xlfn.LET(_xlpm.s,TRIM(_xlfn.TEXTBEFORE(_xlpm.p,"to")),_xlpm.e,TRIM(_xlfn.TEXTAFTER(_xlpm.p,"to")),_xlpm.sd,DATE(VALUE(_xlfn.TEXTAFTER(_xlpm.s,"/",-1)),VALUE(_xlfn.TEXTBEFORE(_xlfn.TEXTAFTER(_xlpm.s,"/"),"/")),VALUE(_xlfn.TEXTBEFORE(_xlpm.s,"/"))),_xlpm.ed,DATE(VALUE(_xlfn.TEXTAFTER(_xlpm.e,"/",-1)),VALUE(_xlfn.TEXTBEFORE(_xlfn.TEXTAFTER(_xlpm.e,"/"),"/")),VALUE(_xlfn.TEXTBEFORE(_xlpm.e,"/"))),_xlpm.ed-_xlpm.sd+1),"-")))} -> 31 | K45: 12/08/2026 to 11/09/2026 | L45: 2 | M45: =IF(OR(L45="",L45="-"),"-",IF(AND(ISNUMBER(I45),I45<>0),I45*L45,IF(ISNUMBER(H45),H45*L45,"-"))) -> 236.44 | N45: =IF(OR(G45="",H45="",L45=""),"",(H45-G45)*L45) -> 97.44 | O45: =IF(OR(G45="",G45=0,H45=""),"",((H45-G45)/G45)*100) -> 3.626943 | P45: SoftwareOne | Q45: Invoice Sent | R45: No
A46: =ROW() - ROW($A$2) -> 44 | B46: 46252 | C46: Caritor Solutions | E46: Renewal | F46: Business Basic (Annual - Annual ) | G46: 1583.04 | H46: 1632 | J46: {=_xlfn.LET(_xlpm.p,K46,IF(OR(_xlpm.p="",_xlpm.p="-",ISERROR(SEARCH("to",_xlpm.p))),"-",IFERROR(_xlfn.LET(_xlpm.s,TRIM(_xlfn.TEXTBEFORE(_xlpm.p,"to")),_xlpm.e,TRIM(_xlfn.TEXTAFTER(_xlpm.p,"to")),_xlpm.sd,DATE(VALUE(_xlfn.TEXTAFTER(_xlpm.s,"/",-1)),VALUE(_xlfn.TEXTBEFORE(_xlfn.TEXTAFTER(_xlpm.s,"/"),"/")),VALUE(_xlfn.TEXTBEFORE(_xlpm.s,"/"))),_xlpm.ed,DATE(VALUE(_xlfn.TEXTAFTER(_xlpm.e,"/",-1)),VALUE(_xlfn.TEXTBEFORE(_xlfn.TEXTAFTER(_xlpm.e,"/"),"/")),VALUE(_xlfn.TEXTBEFORE(_xlpm.e,"/"))),_xlpm.ed-_xlpm.sd+1),"-")))} -> 365 | K46: 18/08/2026 to 17/08/2027 | L46: 1 | M46: =IF(OR(L46="",L46="-"),"-",IF(AND(ISNUMBER(I46),I46<>0),I46*L46,IF(ISNUMBER(H46),H46*L46,"-"))) -> 1632 | N46: =IF(OR(G46="",H46="",L46=""),"",(H46-G46)*L46) -> 48.96 | O46: =IF(OR(G46="",G46=0,H46=""),"",((H46-G46)/G46)*100) -> 3.0927835 | P46: SoftwareOne | Q46: Need to send invoice | R46: No | S46: EVVS Karnataka
A47: =ROW() - ROW($A$2) -> 45 | B47: 46253 | C47: Utthunga Technologies Pvt Ltd | E47: Net New | F47: Visual Studio Professional 2026 | G47: 36184 | H47: 36365 | J47: {=_xlfn.LET(_xlpm.p,K47,IF(OR(_xlpm.p="",_xlpm.p="-",ISERROR(SEARCH("to",_xlpm.p))),"-",IFERROR(_xlfn.LET(_xlpm.s,TRIM(_xlfn.TEXTBEFORE(_xlpm.p,"to")),_xlpm.e,TRIM(_xlfn.TEXTAFTER(_xlpm.p,"to")),_xlpm.sd,DATE(VALUE(_xlfn.TEXTAFTER(_xlpm.s,"/",-1)),VALUE(_xlfn.TEXTBEFORE(_xlfn.TEXTAFTER(_xlpm.s,"/"),"/")),VALUE(_xlfn.TEXTBEFORE(_xlpm.s,"/"))),_xlpm.ed,DATE(VALUE(_xlfn.TEXTAFTER(_xlpm.e,"/",-1)),VALUE(_xlfn.TEXTBEFORE(_xlfn.TEXTAFTER(_xlpm.e,"/"),"/")),VALUE(_xlfn.TEXTBEFORE(_xlpm.e,"/"))),_xlpm.ed-_xlpm.sd+1),"-")))} -> - | K47: Perpetual | L47: 40 | M47: =IF(OR(L47="",L47="-"),"-",IF(AND(ISNUMBER(I47),I47<>0),I47*L47,IF(ISNUMBER(H47),H47*L47,"-"))) -> 1454600 | N47: =IF(OR(G47="",H47="",L47=""),"",(H47-G47)*L47) -> 7240 | O47: =IF(OR(G47="",G47=0,H47=""),"",((H47-G47)/G47)*100) -> 0.50022109 | P47: Tata Tele | Q47: Invoice Sent | R47: No | S47: Raise invoice, but agreed credit period is 30 days.
A48: =ROW() - ROW($A$2) -> 46 | B48: 46253 | C48: INS LABS Pvt Ltd | E48: Prorate | F48: Business Basic (Annual - Annual ) | G48: 1350.24 | H48: 1392 | I48: 1098.35 | J48: {=_xlfn.LET(_xlpm.p,K48,IF(OR(_xlpm.p="",_xlpm.p="-",ISERROR(SEARCH("to",_xlpm.p))),"-",IFERROR(_xlfn.LET(_xlpm.s,TRIM(_xlfn.TEXTBEFORE(_xlpm.p,"to")),_xlpm.e,TRIM(_xlfn.TEXTAFTER(_xlpm.p,"to")),_xlpm.sd,DATE(VALUE(_xlfn.TEXTAFTER(_xlpm.s,"/",-1)),VALUE(_xlfn.TEXTBEFORE(_xlfn.TEXTAFTER(_xlpm.s,"/"),"/")),VALUE(_xlfn.TEXTBEFORE(_xlpm.s,"/"))),_xlpm.ed,DATE(VALUE(_xlfn.TEXTAFTER(_xlpm.e,"/",-1)),VALUE(_xlfn.TEXTBEFORE(_xlfn.TEXTAFTER(_xlpm.e,"/"),"/")),VALUE(_xlfn.TEXTBEFORE(_xlpm.e,"/"))),_xlpm.ed-_xlpm.sd+1),"-")))} -> 288 | K48: 19/08/2026 to 2/6/2027 | L48: 8 | M48: =IF(OR(L48="",L48="-"),"-",IF(AND(ISNUMBER(I48),I48<>0),I48*L48,IF(ISNUMBER(H48),H48*L48,"-"))) -> 8786.8 | N48: =IF(OR(G48="",H48="",L48=""),"",(H48-G48)*L48) -> 334.08 | O48: =IF(OR(G48="",G48=0,H48=""),"",((H48-G48)/G48)*100) -> 3.0927835 | P48: SoftwareOne | Q48: Need to send invoice | R48: No
A49: =ROW() - ROW($A$2) -> 47 | B49: 46254 | C49: Academics and Beyond | E49: Renewal | F49: Business Standard (Annual - Annual) | G49: 8008.32 | H49: 8379.84 | J49: {=_xlfn.LET(_xlpm.p,K49,IF(OR(_xlpm.p="",_xlpm.p="-",ISERROR(SEARCH("to",_xlpm.p))),"-",IFERROR(_xlfn.LET(_xlpm.s,TRIM(_xlfn.TEXTBEFORE(_xlpm.p,"to")),_xlpm.e,TRIM(_xlfn.TEXTAFTER(_xlpm.p,"to")),_xlpm.sd,DATE(VALUE(_xlfn.TEXTAFTER(_xlpm.s,"/",-1)),VALUE(_xlfn.TEXTBEFORE(_xlfn.TEXTAFTER(_xlpm.s,"/"),"/")),VALUE(_xlfn.TEXTBEFORE(_xlpm.s,"/"))),_xlpm.ed,DATE(VALUE(_xlfn.TEXTAFTER(_xlpm.e,"/",-1)),VALUE(_xlfn.TEXTBEFORE(_xlfn.TEXTAFTER(_xlpm.e,"/"),"/")),VALUE(_xlfn.TEXTBEFORE(_xlpm.e,"/"))),_xlpm.ed-_xlpm.sd+1),"-")))} -> 365 | K49: 20/08/2026 to 19/08/2027 | L49: 1 | M49: =IF(OR(L49="",L49="-"),"-",IF(AND(ISNUMBER(I49),I49<>0),I49*L49,IF(ISNUMBER(H49),H49*L49,"-"))) -> 8379.84 | N49: =IF(OR(G49="",H49="",L49=""),"",(H49-G49)*L49) -> 371.52 | O49: =IF(OR(G49="",G49=0,H49=""),"",((H49-G49)/G49)*100) -> 4.6391753 | P49: SoftwareOne | Q49: Need to send invoice | R49: No
A50: =ROW() - ROW($A$2) -> 48 | B50: 46254 | C50: Utthunga Technologies Pvt Ltd | E50: Net New | F50: Planner and Project Plan 3 (Annual - Annual) | G50: 23952 | H50: 24192 | J50: {=_xlfn.LET(_xlpm.p,K50,IF(OR(_xlpm.p="",_xlpm.p="-",ISERROR(SEARCH("to",_xlpm.p))),"-",IFERROR(_xlfn.LET(_xlpm.s,TRIM(_xlfn.TEXTBEFORE(_xlpm.p,"to")),_xlpm.e,TRIM(_xlfn.TEXTAFTER(_xlpm.p,"to")),_xlpm.sd,DATE(VALUE(_xlfn.TEXTAFTER(_xlpm.s,"/",-1)),VALUE(_xlfn.TEXTBEFORE(_xlfn.TEXTAFTER(_xlpm.s,"/"),"/")),VALUE(_xlfn.TEXTBEFORE(_xlpm.s,"/"))),_xlpm.ed,DATE(VALUE(_xlfn.TEXTAFTER(_xlpm.e,"/",-1)),VALUE(_xlfn.TEXTBEFORE(_xlfn.TEXTAFTER(_xlpm.e,"/"),"/")),VALUE(_xlfn.TEXTBEFORE(_xlpm.e,"/"))),_xlpm.ed-_xlpm.sd+1),"-")))} -> 365 | K50: 20/08/2026 to 19/08/2027 | L50: 2 | M50: =IF(OR(L50="",L50="-"),"-",IF(AND(ISNUMBER(I50),I50<>0),I50*L50,IF(ISNUMBER(H50),H50*L50,"-"))) -> 48384 | N50: =IF(OR(G50="",H50="",L50=""),"",(H50-G50)*L50) -> 480 | O50: =IF(OR(G50="",G50=0,H50=""),"",((H50-G50)/G50)*100) -> 1.002004 | P50: Tata Tele | Q50: Invoice Sent | R50: No | S50: Raise invoice, but agreed credit period is 30 days.
A51: =ROW() - ROW($A$2) -> 49 | B51: 46255 | C51: ER Brains IT Solutions | E51: Net New | F51: Teams Premium (Annual - Monthly) | G51: 710.0982 | H51: 717.19918 | J51: {=_xlfn.LET(_xlpm.p,K51,IF(OR(_xlpm.p="",_xlpm.p="-",ISERROR(SEARCH("to",_xlpm.p))),"-",IFERROR(_xlfn.LET(_xlpm.s,TRIM(_xlfn.TEXTBEFORE(_xlpm.p,"to")),_xlpm.e,TRIM(_xlfn.TEXTAFTER(_xlpm.p,"to")),_xlpm.sd,DATE(VALUE(_xlfn.TEXTAFTER(_xlpm.s,"/",-1)),VALUE(_xlfn.TEXTBEFORE(_xlfn.TEXTAFTER(_xlpm.s,"/"),"/")),VALUE(_xlfn.TEXTBEFORE(_xlpm.s,"/"))),_xlpm.ed,DATE(VALUE(_xlfn.TEXTAFTER(_xlpm.e,"/",-1)),VALUE(_xlfn.TEXTBEFORE(_xlfn.TEXTAFTER(_xlpm.e,"/"),"/")),VALUE(_xlfn.TEXTBEFORE(_xlpm.e,"/"))),_xlpm.ed-_xlpm.sd+1),"-")))} -> 365 | K51: 21/08/2026 to 20/08/2027 | L51: 3 | M51: =IF(OR(L51="",L51="-"),"-",IF(AND(ISNUMBER(I51),I51<>0),I51*L51,IF(ISNUMBER(H51),H51*L51,"-"))) -> 2151.5975 | N51: =IF(OR(G51="",H51="",L51=""),"",(H51-G51)*L51) -> 21.302946 | O51: =IF(OR(G51="",G51=0,H51=""),"",((H51-G51)/G51)*100) -> 1 | P51: SoftwareOne | Q51: Need to send invoice | R51: No | S51: 30 days credit period
A52: =ROW() - ROW($A$2) -> 50 | B52: 46257 | C52: Shreenaths Renewables Pvt Ltd | E52: - | F52: Exchange Migration Activity (One-Time) | G52: 0 | H52: 300 | J52: {=_xlfn.LET(_xlpm.p,K52,IF(OR(_xlpm.p="",_xlpm.p="-",ISERROR(SEARCH("to",_xlpm.p))),"-",IFERROR(_xlfn.LET(_xlpm.s,TRIM(_xlfn.TEXTBEFORE(_xlpm.p,"to")),_xlpm.e,TRIM(_xlfn.TEXTAFTER(_xlpm.p,"to")),_xlpm.sd,DATE(VALUE(_xlfn.TEXTAFTER(_xlpm.s,"/",-1)),VALUE(_xlfn.TEXTBEFORE(_xlfn.TEXTAFTER(_xlpm.s,"/"),"/")),VALUE(_xlfn.TEXTBEFORE(_xlpm.s,"/"))),_xlpm.ed,DATE(VALUE(_xlfn.TEXTAFTER(_xlpm.e,"/",-1)),VALUE(_xlfn.TEXTBEFORE(_xlfn.TEXTAFTER(_xlpm.e,"/"),"/")),VALUE(_xlfn.TEXTBEFORE(_xlpm.e,"/"))),_xlpm.ed-_xlpm.sd+1),"-")))} -> - | K52: - | L52: 2 | M52: =IF(OR(L52="",L52="-"),"-",IF(AND(ISNUMBER(I52),I52<>0),I52*L52,IF(ISNUMBER(H52),H52*L52,"-"))) -> 600 | N52: =IF(OR(G52="",H52="",L52=""),"",(H52-G52)*L52) -> 600 | O52: - | Q52: Invoice Sent | R52: No
A53: =ROW() - ROW($A$2) -> 51 | B53: 46258 | C53: SRS Travels | E53: Renewal | F53: Business Basic (Annual - Annual ) | G53: 1583.04 | H53: 1615.68 | J53: {=_xlfn.LET(_xlpm.p,K53,IF(OR(_xlpm.p="",_xlpm.p="-",ISERROR(SEARCH("to",_xlpm.p))),"-",IFERROR(_xlfn.LET(_xlpm.s,TRIM(_xlfn.TEXTBEFORE(_xlpm.p,"to")),_xlpm.e,TRIM(_xlfn.TEXTAFTER(_xlpm.p,"to")),_xlpm.sd,DATE(VALUE(_xlfn.TEXTAFTER(_xlpm.s,"/",-1)),VALUE(_xlfn.TEXTBEFORE(_xlfn.TEXTAFTER(_xlpm.s,"/"),"/")),VALUE(_xlfn.TEXTBEFORE(_xlpm.s,"/"))),_xlpm.ed,DATE(VALUE(_xlfn.TEXTAFTER(_xlpm.e,"/",-1)),VALUE(_xlfn.TEXTBEFORE(_xlfn.TEXTAFTER(_xlpm.e,"/"),"/")),VALUE(_xlfn.TEXTBEFORE(_xlpm.e,"/"))),_xlpm.ed-_xlpm.sd+1),"-")))} -> 365 | K53: 24/08/2026 to 23/08/2027 | L53: 8 | M53: =IF(OR(L53="",L53="-"),"-",IF(AND(ISNUMBER(I53),I53<>0),I53*L53,IF(ISNUMBER(H53),H53*L53,"-"))) -> 12925.44 | N53: =IF(OR(G53="",H53="",L53=""),"",(H53-G53)*L53) -> 261.12 | O53: =IF(OR(G53="",G53=0,H53=""),"",((H53-G53)/G53)*100) -> 2.0618557 | P53: SoftwareOne | Q53: Need to send invoice | R53: No
A54: =ROW() - ROW($A$2) -> 52 | B54: 46258 | C54: Caritor Solutions | E54: Renewal | F54: Business Basic (Annual - Annual ) | G54: 1583.04 | H54: 1607.52 | J54: {=_xlfn.LET(_xlpm.p,K54,IF(OR(_xlpm.p="",_xlpm.p="-",ISERROR(SEARCH("to",_xlpm.p))),"-",IFERROR(_xlfn.LET(_xlpm.s,TRIM(_xlfn.TEXTBEFORE(_xlpm.p,"to")),_xlpm.e,TRIM(_xlfn.TEXTAFTER(_xlpm.p,"to")),_xlpm.sd,DATE(VALUE(_xlfn.TEXTAFTER(_xlpm.s,"/",-1)),VALUE(_xlfn.TEXTBEFORE(_xlfn.TEXTAFTER(_xlpm.s,"/"),"/")),VALUE(_xlfn.TEXTBEFORE(_xlpm.s,"/"))),_xlpm.ed,DATE(VALUE(_xlfn.TEXTAFTER(_xlpm.e,"/",-1)),VALUE(_xlfn.TEXTBEFORE(_xlfn.TEXTAFTER(_xlpm.e,"/"),"/")),VALUE(_xlfn.TEXTBEFORE(_xlpm.e,"/"))),_xlpm.ed-_xlpm.sd+1),"-")))} -> 365 | K54: 24/08/2026 to 23/08/2027 | L54: 40 | M54: =IF(OR(L54="",L54="-"),"-",IF(AND(ISNUMBER(I54),I54<>0),I54*L54,IF(ISNUMBER(H54),H54*L54,"-"))) -> 64300.8 | N54: =IF(OR(G54="",H54="",L54=""),"",(H54-G54)*L54) -> 979.2 | O54: =IF(OR(G54="",G54=0,H54=""),"",((H54-G54)/G54)*100) -> 1.5463918 | P54: SoftwareOne | Q54: Need to send invoice | R54: No
A55: =ROW() - ROW($A$2) -> 53 | B55: 46258 | C55: Malathi Venkat Enterprises | E55: Renewal | F55: Business Basic (Annual - Annual ) | G55: 1615.68 | H55: 1648.32 | J55: {=_xlfn.LET(_xlpm.p,K55,IF(OR(_xlpm.p="",_xlpm.p="-",ISERROR(SEARCH("to",_xlpm.p))),"-",IFERROR(_xlfn.LET(_xlpm.s,TRIM(_xlfn.TEXTBEFORE(_xlpm.p,"to")),_xlpm.e,TRIM(_xlfn.TEXTAFTER(_xlpm.p,"to")),_xlpm.sd,DATE(VALUE(_xlfn.TEXTAFTER(_xlpm.s,"/",-1)),VALUE(_xlfn.TEXTBEFORE(_xlfn.TEXTAFTER(_xlpm.s,"/"),"/")),VALUE(_xlfn.TEXTBEFORE(_xlpm.s,"/"))),_xlpm.ed,DATE(VALUE(_xlfn.TEXTAFTER(_xlpm.e,"/",-1)),VALUE(_xlfn.TEXTBEFORE(_xlfn.TEXTAFTER(_xlpm.e,"/"),"/")),VALUE(_xlfn.TEXTBEFORE(_xlpm.e,"/"))),_xlpm.ed-_xlpm.sd+1),"-")))} -> 365 | K55: 24/08/2026 to 23/08/2027 | L55: 2 | M55: =IF(OR(L55="",L55="-"),"-",IF(AND(ISNUMBER(I55),I55<>0),I55*L55,IF(ISNUMBER(H55),H55*L55,"-"))) -> 3296.64 | N55: =IF(OR(G55="",H55="",L55=""),"",(H55-G55)*L55) -> 65.28 | O55: =IF(OR(G55="",G55=0,H55=""),"",((H55-G55)/G55)*100) -> 2.020202 | P55: Redington | Q55: Invoice Sent | R55: Yes
A56: =ROW() - ROW($A$2) -> 54 | B56: 46259 | C56: Neo TVS | E56: - | F56: Website Hosting Charges | G56: 0 | H56: 1695 | J56: {=_xlfn.LET(_xlpm.p,K56,IF(OR(_xlpm.p="",_xlpm.p="-",ISERROR(SEARCH("to",_xlpm.p))),"-",IFERROR(_xlfn.LET(_xlpm.s,TRIM(_xlfn.TEXTBEFORE(_xlpm.p,"to")),_xlpm.e,TRIM(_xlfn.TEXTAFTER(_xlpm.p,"to")),_xlpm.sd,DATE(VALUE(_xlfn.TEXTAFTER(_xlpm.s,"/",-1)),VALUE(_xlfn.TEXTBEFORE(_xlfn.TEXTAFTER(_xlpm.s,"/"),"/")),VALUE(_xlfn.TEXTBEFORE(_xlpm.s,"/"))),_xlpm.ed,DATE(VALUE(_xlfn.TEXTAFTER(_xlpm.e,"/",-1)),VALUE(_xlfn.TEXTBEFORE(_xlfn.TEXTAFTER(_xlpm.e,"/"),"/")),VALUE(_xlfn.TEXTBEFORE(_xlpm.e,"/"))),_xlpm.ed-_xlpm.sd+1),"-")))} -> 365 | K56: 25/08/2026 to 24/08/2027 | L56: 1 | M56: =IF(OR(L56="",L56="-"),"-",IF(AND(ISNUMBER(I56),I56<>0),I56*L56,IF(ISNUMBER(H56),H56*L56,"-"))) -> 1695 | N56: =IF(OR(G56="",H56="",L56=""),"",(H56-G56)*L56) -> 1695 | O56: - | Q56: Invoice Sent | R56: No | S56: Share the GST invoice to Neo TVS
A57: =ROW() - ROW($A$2) -> 55 | B57: 46261 | C57: Sudarrshan Tech Services | E57: Net New | F57: Business Basic (Annual - Annual ) | G57: 1607.52 | H57: 1648.32 | J57: {=_xlfn.LET(_xlpm.p,K57,IF(OR(_xlpm.p="",_xlpm.p="-",ISERROR(SEARCH("to",_xlpm.p))),"-",IFERROR(_xlfn.LET(_xlpm.s,TRIM(_xlfn.TEXTBEFORE(_xlpm.p,"to")),_xlpm.e,TRIM(_xlfn.TEXTAFTER(_xlpm.p,"to")),_xlpm.sd,DATE(VALUE(_xlfn.TEXTAFTER(_xlpm.s,"/",-1)),VALUE(_xlfn.TEXTBEFORE(_xlfn.TEXTAFTER(_xlpm.s,"/"),"/")),VALUE(_xlfn.TEXTBEFORE(_xlpm.s,"/"))),_xlpm.ed,DATE(VALUE(_xlfn.TEXTAFTER(_xlpm.e,"/",-1)),VALUE(_xlfn.TEXTBEFORE(_xlfn.TEXTAFTER(_xlpm.e,"/"),"/")),VALUE(_xlfn.TEXTBEFORE(_xlpm.e,"/"))),_xlpm.ed-_xlpm.sd+1),"-")))} -> 365 | K57: 27/08/2026 to 26/08/2027 | L57: 11 | M57: =IF(OR(L57="",L57="-"),"-",IF(AND(ISNUMBER(I57),I57<>0),I57*L57,IF(ISNUMBER(H57),H57*L57,"-"))) -> 18131.52 | N57: =IF(OR(G57="",H57="",L57=""),"",(H57-G57)*L57) -> 448.8 | O57: =IF(OR(G57="",G57=0,H57=""),"",((H57-G57)/G57)*100) -> 2.5380711 | P57: Redington | Q57: Invoice Sent | R57: No | S57: Share the GST invoice to Sudarrshan Tech
A58: =ROW() - ROW($A$2) -> 56 | F58: Business Standard (no Teams) (Annual - Annual) | G58: 6288.24 | H58: 6447.84 | J58: {=_xlfn.LET(_xlpm.p,K58,IF(OR(_xlpm.p="",_xlpm.p="-",ISERROR(SEARCH("to",_xlpm.p))),"-",IFERROR(_xlfn.LET(_xlpm.s,TRIM(_xlfn.TEXTBEFORE(_xlpm.p,"to")),_xlpm.e,TRIM(_xlfn.TEXTAFTER(_xlpm.p,"to")),_xlpm.sd,DATE(VALUE(_xlfn.TEXTAFTER(_xlpm.s,"/",-1)),VALUE(_xlfn.TEXTBEFORE(_xlfn.TEXTAFTER(_xlpm.s,"/"),"/")),VALUE(_xlfn.TEXTBEFORE(_xlpm.s,"/"))),_xlpm.ed,DATE(VALUE(_xlfn.TEXTAFTER(_xlpm.e,"/",-1)),VALUE(_xlfn.TEXTBEFORE(_xlfn.TEXTAFTER(_xlpm.e,"/"),"/")),VALUE(_xlfn.TEXTBEFORE(_xlpm.e,"/"))),_xlpm.ed-_xlpm.sd+1),"-")))} -> 365 | K58: 27/08/2026 to 26/08/2027 | L58: 1 | M58: =IF(OR(L58="",L58="-"),"-",IF(AND(ISNUMBER(I58),I58<>0),I58*L58,IF(ISNUMBER(H58),H58*L58,"-"))) -> 6447.84 | N58: =IF(OR(G58="",H58="",L58=""),"",(H58-G58)*L58) -> 159.6 | O58: =IF(OR(G58="",G58=0,H58=""),"",((H58-G58)/G58)*100) -> 2.5380711 | P58: Redington
A59: =ROW() - ROW($A$2) -> 57 | F59: Exchange Online Archiving for Exchange Online (Annual - Annual) | G59: 2400 | H59: 2424 | J59: {=_xlfn.LET(_xlpm.p,K59,IF(OR(_xlpm.p="",_xlpm.p="-",ISERROR(SEARCH("to",_xlpm.p))),"-",IFERROR(_xlfn.LET(_xlpm.s,TRIM(_xlfn.TEXTBEFORE(_xlpm.p,"to")),_xlpm.e,TRIM(_xlfn.TEXTAFTER(_xlpm.p,"to")),_xlpm.sd,DATE(VALUE(_xlfn.TEXTAFTER(_xlpm.s,"/",-1)),VALUE(_xlfn.TEXTBEFORE(_xlfn.TEXTAFTER(_xlpm.s,"/"),"/")),VALUE(_xlfn.TEXTBEFORE(_xlpm.s,"/"))),_xlpm.ed,DATE(VALUE(_xlfn.TEXTAFTER(_xlpm.e,"/",-1)),VALUE(_xlfn.TEXTBEFORE(_xlfn.TEXTAFTER(_xlpm.e,"/"),"/")),VALUE(_xlfn.TEXTBEFORE(_xlpm.e,"/"))),_xlpm.ed-_xlpm.sd+1),"-")))} -> 365 | K59: 27/08/2026 to 26/08/2027 | L59: 1 | M59: =IF(OR(L59="",L59="-"),"-",IF(AND(ISNUMBER(I59),I59<>0),I59*L59,IF(ISNUMBER(H59),H59*L59,"-"))) -> 2424 | N59: =IF(OR(G59="",H59="",L59=""),"",(H59-G59)*L59) -> 24 | O59: =IF(OR(G59="",G59=0,H59=""),"",((H59-G59)/G59)*100) -> 1 | P59: Redington
A60: =ROW() - ROW($A$2) -> 58 | J60: {=_xlfn.LET(_xlpm.p,K60,IF(OR(_xlpm.p="",_xlpm.p="-",ISERROR(SEARCH("to",_xlpm.p))),"-",IFERROR(_xlfn.LET(_xlpm.s,TRIM(_xlfn.TEXTBEFORE(_xlpm.p,"to")),_xlpm.e,TRIM(_xlfn.TEXTAFTER(_xlpm.p,"to")),_xlpm.sd,DATE(VALUE(_xlfn.TEXTAFTER(_xlpm.s,"/",-1)),VALUE(_xlfn.TEXTBEFORE(_xlfn.TEXTAFTER(_xlpm.s,"/"),"/")),VALUE(_xlfn.TEXTBEFORE(_xlpm.s,"/"))),_xlpm.ed,DATE(VALUE(_xlfn.TEXTAFTER(_xlpm.e,"/",-1)),VALUE(_xlfn.TEXTBEFORE(_xlfn.TEXTAFTER(_xlpm.e,"/"),"/")),VALUE(_xlfn.TEXTBEFORE(_xlpm.e,"/"))),_xlpm.ed-_xlpm.sd+1),"-")))} -> - | M60: =IF(OR(L60="",L60="-"),"-",IF(AND(ISNUMBER(I60),I60<>0),I60*L60,IF(ISNUMBER(H60),H60*L60,"-"))) -> - | N60: =IF(OR(G60="",H60="",L60=""),"",(H60-G60)*L60) | O60: =IF(OR(G60="",G60=0,H60=""),"",((H60-G60)/G60)*100)
A61: =ROW() - ROW($A$2) -> 59 | J61: {=_xlfn.LET(_xlpm.p,K61,IF(OR(_xlpm.p="",_xlpm.p="-",ISERROR(SEARCH("to",_xlpm.p))),"-",IFERROR(_xlfn.LET(_xlpm.s,TRIM(_xlfn.TEXTBEFORE(_xlpm.p,"to")),_xlpm.e,TRIM(_xlfn.TEXTAFTER(_xlpm.p,"to")),_xlpm.sd,DATE(VALUE(_xlfn.TEXTAFTER(_xlpm.s,"/",-1)),VALUE(_xlfn.TEXTBEFORE(_xlfn.TEXTAFTER(_xlpm.s,"/"),"/")),VALUE(_xlfn.TEXTBEFORE(_xlpm.s,"/"))),_xlpm.ed,DATE(VALUE(_xlfn.TEXTAFTER(_xlpm.e,"/",-1)),VALUE(_xlfn.TEXTBEFORE(_xlfn.TEXTAFTER(_xlpm.e,"/"),"/")),VALUE(_xlfn.TEXTBEFORE(_xlpm.e,"/"))),_xlpm.ed-_xlpm.sd+1),"-")))} -> - | M61: =IF(OR(L61="",L61="-"),"-",IF(AND(ISNUMBER(I61),I61<>0),I61*L61,IF(ISNUMBER(H61),H61*L61,"-"))) -> - | N61: =IF(OR(G61="",H61="",L61=""),"",(H61-G61)*L61) | O61: =IF(OR(G61="",G61=0,H61=""),"",((H61-G61)/G61)*100)
A62: =ROW() - ROW($A$2) -> 60 | J62: {=_xlfn.LET(_xlpm.p,K62,IF(OR(_xlpm.p="",_xlpm.p="-",ISERROR(SEARCH("to",_xlpm.p))),"-",IFERROR(_xlfn.LET(_xlpm.s,TRIM(_xlfn.TEXTBEFORE(_xlpm.p,"to")),_xlpm.e,TRIM(_xlfn.TEXTAFTER(_xlpm.p,"to")),_xlpm.sd,DATE(VALUE(_xlfn.TEXTAFTER(_xlpm.s,"/",-1)),VALUE(_xlfn.TEXTBEFORE(_xlfn.TEXTAFTER(_xlpm.s,"/"),"/")),VALUE(_xlfn.TEXTBEFORE(_xlpm.s,"/"))),_xlpm.ed,DATE(VALUE(_xlfn.TEXTAFTER(_xlpm.e,"/",-1)),VALUE(_xlfn.TEXTBEFORE(_xlfn.TEXTAFTER(_xlpm.e,"/"),"/")),VALUE(_xlfn.TEXTBEFORE(_xlpm.e,"/"))),_xlpm.ed-_xlpm.sd+1),"-")))} -> - | M62: =IF(OR(L62="",L62="-"),"-",IF(AND(ISNUMBER(I62),I62<>0),I62*L62,IF(ISNUMBER(H62),H62*L62,"-"))) -> - | N62: =IF(OR(G62="",H62="",L62=""),"",(H62-G62)*L62) | O62: =IF(OR(G62="",G62=0,H62=""),"",((H62-G62)/G62)*100)
A63: =ROW() - ROW($A$2) -> 61 | J63: {=_xlfn.LET(_xlpm.p,K63,IF(OR(_xlpm.p="",_xlpm.p="-",ISERROR(SEARCH("to",_xlpm.p))),"-",IFERROR(_xlfn.LET(_xlpm.s,TRIM(_xlfn.TEXTBEFORE(_xlpm.p,"to")),_xlpm.e,TRIM(_xlfn.TEXTAFTER(_xlpm.p,"to")),_xlpm.sd,DATE(VALUE(_xlfn.TEXTAFTER(_xlpm.s,"/",-1)),VALUE(_xlfn.TEXTBEFORE(_xlfn.TEXTAFTER(_xlpm.s,"/"),"/")),VALUE(_xlfn.TEXTBEFORE(_xlpm.s,"/"))),_xlpm.ed,DATE(VALUE(_xlfn.TEXTAFTER(_xlpm.e,"/",-1)),VALUE(_xlfn.TEXTBEFORE(_xlfn.TEXTAFTER(_xlpm.e,"/"),"/")),VALUE(_xlfn.TEXTBEFORE(_xlpm.e,"/"))),_xlpm.ed-_xlpm.sd+1),"-")))} -> - | M63: =IF(OR(L63="",L63="-"),"-",IF(AND(ISNUMBER(I63),I63<>0),I63*L63,IF(ISNUMBER(H63),H63*L63,"-"))) -> - | N63: =IF(OR(G63="",H63="",L63=""),"",(H63-G63)*L63) | O63: =IF(OR(G63="",G63=0,H63=""),"",((H63-G63)/G63)*100)
A64: =ROW() - ROW($A$2) -> 62 | J64: {=_xlfn.LET(_xlpm.p,K64,IF(OR(_xlpm.p="",_xlpm.p="-",ISERROR(SEARCH("to",_xlpm.p))),"-",IFERROR(_xlfn.LET(_xlpm.s,TRIM(_xlfn.TEXTBEFORE(_xlpm.p,"to")),_xlpm.e,TRIM(_xlfn.TEXTAFTER(_xlpm.p,"to")),_xlpm.sd,DATE(VALUE(_xlfn.TEXTAFTER(_xlpm.s,"/",-1)),VALUE(_xlfn.TEXTBEFORE(_xlfn.TEXTAFTER(_xlpm.s,"/"),"/")),VALUE(_xlfn.TEXTBEFORE(_xlpm.s,"/"))),_xlpm.ed,DATE(VALUE(_xlfn.TEXTAFTER(_xlpm.e,"/",-1)),VALUE(_xlfn.TEXTBEFORE(_xlfn.TEXTAFTER(_xlpm.e,"/"),"/")),VALUE(_xlfn.TEXTBEFORE(_xlpm.e,"/"))),_xlpm.ed-_xlpm.sd+1),"-")))} -> - | M64: =IF(OR(L64="",L64="-"),"-",IF(AND(ISNUMBER(I64),I64<>0),I64*L64,IF(ISNUMBER(H64),H64*L64,"-"))) -> - | N64: =IF(OR(G64="",H64="",L64=""),"",(H64-G64)*L64) | O64: =IF(OR(G64="",G64=0,H64=""),"",((H64-G64)/G64)*100)
A65: =ROW() - ROW($A$2) -> 63 | J65: {=_xlfn.LET(_xlpm.p,K65,IF(OR(_xlpm.p="",_xlpm.p="-",ISERROR(SEARCH("to",_xlpm.p))),"-",IFERROR(_xlfn.LET(_xlpm.s,TRIM(_xlfn.TEXTBEFORE(_xlpm.p,"to")),_xlpm.e,TRIM(_xlfn.TEXTAFTER(_xlpm.p,"to")),_xlpm.sd,DATE(VALUE(_xlfn.TEXTAFTER(_xlpm.s,"/",-1)),VALUE(_xlfn.TEXTBEFORE(_xlfn.TEXTAFTER(_xlpm.s,"/"),"/")),VALUE(_xlfn.TEXTBEFORE(_xlpm.s,"/"))),_xlpm.ed,DATE(VALUE(_xlfn.TEXTAFTER(_xlpm.e,"/",-1)),VALUE(_xlfn.TEXTBEFORE(_xlfn.TEXTAFTER(_xlpm.e,"/"),"/")),VALUE(_xlfn.TEXTBEFORE(_xlpm.e,"/"))),_xlpm.ed-_xlpm.sd+1),"-")))} -> - | M65: =IF(OR(L65="",L65="-"),"-",IF(AND(ISNUMBER(I65),I65<>0),I65*L65,IF(ISNUMBER(H65),H65*L65,"-"))) -> - | N65: =IF(OR(G65="",H65="",L65=""),"",(H65-G65)*L65) | O65: =IF(OR(G65="",G65=0,H65=""),"",((H65-G65)/G65)*100)
A66: =ROW() - ROW($A$2) -> 64 | J66: {=_xlfn.LET(_xlpm.p,K66,IF(OR(_xlpm.p="",_xlpm.p="-",ISERROR(SEARCH("to",_xlpm.p))),"-",IFERROR(_xlfn.LET(_xlpm.s,TRIM(_xlfn.TEXTBEFORE(_xlpm.p,"to")),_xlpm.e,TRIM(_xlfn.TEXTAFTER(_xlpm.p,"to")),_xlpm.sd,DATE(VALUE(_xlfn.TEXTAFTER(_xlpm.s,"/",-1)),VALUE(_xlfn.TEXTBEFORE(_xlfn.TEXTAFTER(_xlpm.s,"/"),"/")),VALUE(_xlfn.TEXTBEFORE(_xlpm.s,"/"))),_xlpm.ed,DATE(VALUE(_xlfn.TEXTAFTER(_xlpm.e,"/",-1)),VALUE(_xlfn.TEXTBEFORE(_xlfn.TEXTAFTER(_xlpm.e,"/"),"/")),VALUE(_xlfn.TEXTBEFORE(_xlpm.e,"/"))),_xlpm.ed-_xlpm.sd+1),"-")))} -> - | M66: =IF(OR(L66="",L66="-"),"-",IF(AND(ISNUMBER(I66),I66<>0),I66*L66,IF(ISNUMBER(H66),H66*L66,"-"))) -> - | N66: =IF(OR(G66="",H66="",L66=""),"",(H66-G66)*L66) | O66: =IF(OR(G66="",G66=0,H66=""),"",((H66-G66)/G66)*100)
A67: =ROW() - ROW($A$2) -> 65 | J67: {=_xlfn.LET(_xlpm.p,K67,IF(OR(_xlpm.p="",_xlpm.p="-",ISERROR(SEARCH("to",_xlpm.p))),"-",IFERROR(_xlfn.LET(_xlpm.s,TRIM(_xlfn.TEXTBEFORE(_xlpm.p,"to")),_xlpm.e,TRIM(_xlfn.TEXTAFTER(_xlpm.p,"to")),_xlpm.sd,DATE(VALUE(_xlfn.TEXTAFTER(_xlpm.s,"/",-1)),VALUE(_xlfn.TEXTBEFORE(_xlfn.TEXTAFTER(_xlpm.s,"/"),"/")),VALUE(_xlfn.TEXTBEFORE(_xlpm.s,"/"))),_xlpm.ed,DATE(VALUE(_xlfn.TEXTAFTER(_xlpm.e,"/",-1)),VALUE(_xlfn.TEXTBEFORE(_xlfn.TEXTAFTER(_xlpm.e,"/"),"/")),VALUE(_xlfn.TEXTBEFORE(_xlpm.e,"/"))),_xlpm.ed-_xlpm.sd+1),"-")))} -> - | M67: =IF(OR(L67="",L67="-"),"-",IF(AND(ISNUMBER(I67),I67<>0),I67*L67,IF(ISNUMBER(H67),H67*L67,"-"))) -> - | N67: =IF(OR(G67="",H67="",L67=""),"",(H67-G67)*L67) | O67: =IF(OR(G67="",G67=0,H67=""),"",((H67-G67)/G67)*100)
A68: =ROW() - ROW($A$2) -> 66 | J68: {=_xlfn.LET(_xlpm.p,K68,IF(OR(_xlpm.p="",_xlpm.p="-",ISERROR(SEARCH("to",_xlpm.p))),"-",IFERROR(_xlfn.LET(_xlpm.s,TRIM(_xlfn.TEXTBEFORE(_xlpm.p,"to")),_xlpm.e,TRIM(_xlfn.TEXTAFTER(_xlpm.p,"to")),_xlpm.sd,DATE(VALUE(_xlfn.TEXTAFTER(_xlpm.s,"/",-1)),VALUE(_xlfn.TEXTBEFORE(_xlfn.TEXTAFTER(_xlpm.s,"/"),"/")),VALUE(_xlfn.TEXTBEFORE(_xlpm.s,"/"))),_xlpm.ed,DATE(VALUE(_xlfn.TEXTAFTER(_xlpm.e,"/",-1)),VALUE(_xlfn.TEXTBEFORE(_xlfn.TEXTAFTER(_xlpm.e,"/"),"/")),VALUE(_xlfn.TEXTBEFORE(_xlpm.e,"/"))),_xlpm.ed-_xlpm.sd+1),"-")))} -> - | M68: =IF(OR(L68="",L68="-"),"-",IF(AND(ISNUMBER(I68),I68<>0),I68*L68,IF(ISNUMBER(H68),H68*L68,"-"))) -> - | N68: =IF(OR(G68="",H68="",L68=""),"",(H68-G68)*L68) | O68: =IF(OR(G68="",G68=0,H68=""),"",((H68-G68)/G68)*100)
A69: =ROW() - ROW($A$2) -> 67 | J69: {=_xlfn.LET(_xlpm.p,K69,IF(OR(_xlpm.p="",_xlpm.p="-",ISERROR(SEARCH("to",_xlpm.p))),"-",IFERROR(_xlfn.LET(_xlpm.s,TRIM(_xlfn.TEXTBEFORE(_xlpm.p,"to")),_xlpm.e,TRIM(_xlfn.TEXTAFTER(_xlpm.p,"to")),_xlpm.sd,DATE(VALUE(_xlfn.TEXTAFTER(_xlpm.s,"/",-1)),VALUE(_xlfn.TEXTBEFORE(_xlfn.TEXTAFTER(_xlpm.s,"/"),"/")),VALUE(_xlfn.TEXTBEFORE(_xlpm.s,"/"))),_xlpm.ed,DATE(VALUE(_xlfn.TEXTAFTER(_xlpm.e,"/",-1)),VALUE(_xlfn.TEXTBEFORE(_xlfn.TEXTAFTER(_xlpm.e,"/"),"/")),VALUE(_xlfn.TEXTBEFORE(_xlpm.e,"/"))),_xlpm.ed-_xlpm.sd+1),"-")))} -> - | M69: =IF(OR(L69="",L69="-"),"-",IF(AND(ISNUMBER(I69),I69<>0),I69*L69,IF(ISNUMBER(H69),H69*L69,"-"))) -> - | N69: =IF(OR(G69="",H69="",L69=""),"",(H69-G69)*L69) | O69: =IF(OR(G69="",G69=0,H69=""),"",((H69-G69)/G69)*100)
A70: =ROW() - ROW($A$2) -> 68 | J70: {=_xlfn.LET(_xlpm.p,K70,IF(OR(_xlpm.p="",_xlpm.p="-",ISERROR(SEARCH("to",_xlpm.p))),"-",IFERROR(_xlfn.LET(_xlpm.s,TRIM(_xlfn.TEXTBEFORE(_xlpm.p,"to")),_xlpm.e,TRIM(_xlfn.TEXTAFTER(_xlpm.p,"to")),_xlpm.sd,DATE(VALUE(_xlfn.TEXTAFTER(_xlpm.s,"/",-1)),VALUE(_xlfn.TEXTBEFORE(_xlfn.TEXTAFTER(_xlpm.s,"/"),"/")),VALUE(_xlfn.TEXTBEFORE(_xlpm.s,"/"))),_xlpm.ed,DATE(VALUE(_xlfn.TEXTAFTER(_xlpm.e,"/",-1)),VALUE(_xlfn.TEXTBEFORE(_xlfn.TEXTAFTER(_xlpm.e,"/"),"/")),VALUE(_xlfn.TEXTBEFORE(_xlpm.e,"/"))),_xlpm.ed-_xlpm.sd+1),"-")))} -> - | M70: =IF(OR(L70="",L70="-"),"-",IF(AND(ISNUMBER(I70),I70<>0),I70*L70,IF(ISNUMBER(H70),H70*L70,"-"))) -> - | N70: =IF(OR(G70="",H70="",L70=""),"",(H70-G70)*L70) | O70: =IF(OR(G70="",G70=0,H70=""),"",((H70-G70)/G70)*100)
A71: =ROW() - ROW($A$2) -> 69 | J71: {=_xlfn.LET(_xlpm.p,K71,IF(OR(_xlpm.p="",_xlpm.p="-",ISERROR(SEARCH("to",_xlpm.p))),"-",IFERROR(_xlfn.LET(_xlpm.s,TRIM(_xlfn.TEXTBEFORE(_xlpm.p,"to")),_xlpm.e,TRIM(_xlfn.TEXTAFTER(_xlpm.p,"to")),_xlpm.sd,DATE(VALUE(_xlfn.TEXTAFTER(_xlpm.s,"/",-1)),VALUE(_xlfn.TEXTBEFORE(_xlfn.TEXTAFTER(_xlpm.s,"/"),"/")),VALUE(_xlfn.TEXTBEFORE(_xlpm.s,"/"))),_xlpm.ed,DATE(VALUE(_xlfn.TEXTAFTER(_xlpm.e,"/",-1)),VALUE(_xlfn.TEXTBEFORE(_xlfn.TEXTAFTER(_xlpm.e,"/"),"/")),VALUE(_xlfn.TEXTBEFORE(_xlpm.e,"/"))),_xlpm.ed-_xlpm.sd+1),"-")))} -> - | M71: =IF(OR(L71="",L71="-"),"-",IF(AND(ISNUMBER(I71),I71<>0),I71*L71,IF(ISNUMBER(H71),H71*L71,"-"))) -> - | N71: =IF(OR(G71="",H71="",L71=""),"",(H71-G71)*L71) | O71: =IF(OR(G71="",G71=0,H71=""),"",((H71-G71)/G71)*100)
... A100: =ROW() - ROW($A$2) -> 98 | J100: {=_xlfn.LET(_xlpm.p,K100,IF(OR(_xlpm.p="",_xlpm.p="-",ISERROR(SEARCH("to",_xlpm.p))),"-",IFERROR(_xlfn.LET(_xlpm.s,TRIM(_xlfn.TEXTBEFORE(_xlpm.p,"to")),_xlpm.e,TRIM(_xlfn.TEXTAFTER(_xlpm.p,"to")),_xlpm.sd,DATE(VALUE(_xlfn.TEXTAFTER(_xlpm.s,"/",-1)),VALUE(_xlfn.TEXTBEFORE(_xlfn.TEXTAFTER(_xlpm.s,"/"),"/")),VALUE(_xlfn.TEXTBEFORE(_xlpm.s,"/"))),_xlpm.ed,DATE(VALUE(_xlfn.TEXTAFTER(_xlpm.e,"/",-1)),VALUE(_xlfn.TEXTBEFORE(_xlfn.TEXTAFTER(_xlpm.e,"/"),"/")),VALUE(_xlfn.TEXTBEFORE(_xlpm.e,"/"))),_xlpm.ed-_xlpm.sd+1),"-")))} -> - | M100: =IF(OR(L100="",L100="-"),"-",IF(AND(ISNUMBER(I100),I100<>0),I100*L100,IF(ISNUMBER(H100),H100*L100,"-"))) -> - | N100: =IF(OR(G100="",H100="",L100=""),"",(H100-G100)*L100) | O100: =IF(OR(G100="",G100=0,H100=""),"",((H100-G100)/G100)*100)
A101: 53 | B101: 46266 | C101: NuGRP Solutions LLP | E101: Net New | F101: Windows Server 2025 - 1 Device CAL | G101: 2871 | H101: 2960 | J101: - | K101: Perpetual | L101: 12 | M101: =IF(OR(L101="",L101="-"),"-",IF(AND(ISNUMBER(I101),I101<>0),I101*L101,IF(ISNUMBER(H101),H101*L101,"-"))) -> 35520 | N101: =IF(OR(G101="",H101="",L101=""),"",(H101-G101)*L101) -> 1068 | O101: =IF(OR(G101="",G101=0,H101=""),"",((H101-G101)/G101)*100) -> 3.0999652 | P101: Tata Tele | Q101: Need to send invoice | R101: No
F102: SQL Server 2025 - 1 User CAL | G102: 16671 | H102: 17189 | J102: - | L102: 5 | M102: =IF(OR(L102="",L102="-"),"-",IF(AND(ISNUMBER(I102),I102<>0),I102*L102,IF(ISNUMBER(H102),H102*L102,"-"))) -> 85945 | N102: =IF(OR(G102="",H102="",L102=""),"",(H102-G102)*L102) -> 2590 | O102: =IF(OR(G102="",G102=0,H102=""),"",((H102-G102)/G102)*100) -> 3.1071921
F103: SQL Server 2025 Standard edition Perpetual 1 Server License | G103: 71631 | H103: 73855 | J103: - | L103: 1 | M103: =IF(OR(L103="",L103="-"),"-",IF(AND(ISNUMBER(I103),I103<>0),I103*L103,IF(ISNUMBER(H103),H103*L103,"-"))) -> 73855 | N103: =IF(OR(G103="",H103="",L103=""),"",(H103-G103)*L103) -> 2224 | O103: =IF(OR(G103="",G103=0,H103=""),"",((H103-G103)/G103)*100) -> 3.104801

Sheet Vendors
A1: Distributors | E1: Customer List
F2: FinAks Advisory Pvt Ltd
A3: Redington | F3: Cloudwave Technologies Pvt Ltd
A4: SoftwareOne | F4: Krisam Automation Pvt Ltd
A5: Tata Tele | F5: SRS Travels
F6: Sudarrshan Tech Services
F7: Dassworld
A8: Yes | F8: Atomstrings
A9: No | F9: Infiniminds Pvt Ltd
A10: Credit Note | F10: GRP Solutions
A11: Not Applicable | F11: INS LABS Pvt Ltd
F12: TechsharingB
F13: Shreenaths Sustainables Pvt Ltd
F14: NuGRP Solutions LLP
F15: Neo TVS
F16: ER Brains IT Solutions
F17: NexGen Robotics Automation
F18: Whitepaper Solutions
F19: CNC India
F20: Shreenaths Renewables Pvt Ltd
F21: QL Partners
F22: AJM CNC Tool Tech
F23: Caritor Solutions
... F27: EVVS Karnataka
